[{"Country":"Nigeria","Currency":"NGN","Mobile":"1600","Standard with ads":"","Basic":"2900","Standard":"4000","Premium":"5000","Extra member slots":"","MobileUSD":"1.14","With_Ads_USD":"","BasicUSD":"2.06","StandardUSD":"2.84","PremiumUSD":"3.55","MobileCNY":"8.17","With_Ads_CNY":"","BasicCNY":"14.82","StandardCNY":"20.44","PremiumCNY":"25.55","Code":"NG","Translation":"尼日利亚"},{"Country":"Egypt","Currency":"EGP","Mobile":"","Standard with ads":"","Basic":"70","Standard":"120","Premium":"165","Extra member slots":"","MobileUSD":"","With_Ads_USD":"","BasicUSD":"1.49","StandardUSD":"2.56","PremiumUSD":"3.52","MobileCNY":"","With_Ads_CNY":"","BasicCNY":"10.73","StandardCNY":"18.40","PremiumCNY":"25.30","Code":"EG","Translation":"埃及"},{"Country":"Pakistan","Currency":"PKR","Mobile":"250","Standard with ads":"","Basic":"450","Standard":"800","Premium":"1100","Extra member slots":"","MobileUSD":"0.91","With_Ads_USD":"","BasicUSD":"1.63","StandardUSD":"2.90","PremiumUSD":"3.98","MobileCNY":"6.52","With_Ads_CNY":"","BasicCNY":"11.74","StandardCNY":"20.86","PremiumCNY":"28.69","Code":"PK","Translation":"巴基斯坦"},{"Country":"Argentina","Currency":"ARS","Mobile":"","Standard with ads":"","Basic":"2499","Standard":"4199","Premium":"5799","Extra member slots":"Standard: 1399 / Premium: 1399","MobileUSD":"","With_Ads_USD":"","BasicUSD":"2.93","StandardUSD":"4.92","PremiumUSD":"6.80","MobileCNY":"","With_Ads_CNY":"","BasicCNY":"21.09","StandardCNY":"35.43","PremiumCNY":"48.93","Code":"AR","Translation":"阿根廷"},{"Country":"Türkiye","Currency":"TRY","Mobile":"","Standard with ads":"","Basic":"119.99","Standard":"176.99","Premium":"229.99","Extra member slots":"","MobileUSD":"","With_Ads_USD":"","BasicUSD":"3.70","StandardUSD":"5.46","PremiumUSD":"7.09","MobileCNY":"","With_Ads_CNY":"","BasicCNY":"26.64","StandardCNY":"39.30","PremiumCNY":"51.07","Code":"TR","Translation":"土耳其"},{"Country":"India","Currency":"INR","Mobile":"149","Standard with ads":"","Basic":"199","Standard":"499","Premium":"649","Extra member slots":"","MobileUSD":"1.79","With_Ads_USD":"","BasicUSD":"2.39","StandardUSD":"6.00","PremiumUSD":"7.81","MobileCNY":"12.91","With_Ads_CNY":"","BasicCNY":"17.24","StandardCNY":"43.22","PremiumCNY":"56.21","Code":"IN","Translation":"印度"},{"Country":"Belize","Currency":"USD","Mobile":"","Standard with ads":"","Basic":"3.99","Standard":"5.99","Premium":"7.99","Extra member slots":"Standard: 2.99 / Premium: 2.99","MobileUSD":"","With_Ads_USD":"","BasicUSD":"3.99","StandardUSD":"5.99","PremiumUSD":"7.99","MobileCNY":"","With_Ads_CNY":"","BasicCNY":"28.73","StandardCNY":"43.12","PremiumCNY":"57.52","Code":"BZ","Translation":"伯利兹"},{"Country":"Bolivia","Currency":"USD","Mobile":"","Standard with ads":"","Basic":"3.99","Standard":"5.99","Premium":"7.99","Extra member slots":"Standard: 2.99 / Premium: 2.99","MobileUSD":"","With_Ads_USD":"","BasicUSD":"3.99","StandardUSD":"5.99","PremiumUSD":"7.99","MobileCNY":"","With_Ads_CNY":"","BasicCNY":"28.73","StandardCNY":"43.12","PremiumCNY":"57.52","Code":"BO","Translation":"玻利维亚"},{"Country":"Cuba","Currency":"USD","Mobile":"","Standard with ads":"","Basic":"3.99","Standard":"5.99","Premium":"7.99","Extra member slots":"Standard: 2.99 / Premium: 2.99","MobileUSD":"","With_Ads_USD":"","BasicUSD":"3.99","StandardUSD":"5.99","PremiumUSD":"7.99","MobileCNY":"","With_Ads_CNY":"","BasicCNY":"28.73","StandardCNY":"43.12","PremiumCNY":"57.52","Code":"CU","Translation":"古巴"},{"Country":"Dominica","Currency":"USD","Mobile":"","Standard with ads":"","Basic":"3.99","Standard":"5.99","Premium":"7.99","Extra member slots":"Standard: 2.99 / Premium: 2.99","MobileUSD":"","With_Ads_USD":"","BasicUSD":"3.99","StandardUSD":"5.99","PremiumUSD":"7.99","MobileCNY":"","With_Ads_CNY":"","BasicCNY":"28.73","StandardCNY":"43.12","PremiumCNY":"57.52","Code":"DM","Translation":"多米尼加"},{"Country":"Grenada","Currency":"USD","Mobile":"","Standard with ads":"","Basic":"3.99","Standard":"5.99","Premium":"7.99","Extra member slots":"Standard: 2.99 / Premium: 2.99","MobileUSD":"","With_Ads_USD":"","BasicUSD":"3.99","StandardUSD":"5.99","PremiumUSD":"7.99","MobileCNY":"","With_Ads_CNY":"","BasicCNY":"28.73","StandardCNY":"43.12","PremiumCNY":"57.52","Code":"GD","Translation":"格林纳达"},{"Country":"Guyana","Currency":"USD","Mobile":"","Standard with ads":"","Basic":"3.99","Standard":"5.99","Premium":"7.99","Extra member slots":"Standard: 2.99 / Premium: 2.99","MobileUSD":"","With_Ads_USD":"","BasicUSD":"3.99","StandardUSD":"5.99","PremiumUSD":"7.99","MobileCNY":"","With_Ads_CNY":"","BasicCNY":"28.73","StandardCNY":"43.12","PremiumCNY":"57.52","Code":"GY","Translation":"圭亚那"},{"Country":"Haiti","Currency":"USD","Mobile":"","Standard with ads":"","Basic":"3.99","Standard":"5.99","Premium":"7.99","Extra member slots":"Standard: 2.99 / Premium: 2.99","MobileUSD":"","With_Ads_USD":"","BasicUSD":"3.99","StandardUSD":"5.99","PremiumUSD":"7.99","MobileCNY":"","With_Ads_CNY":"","BasicCNY":"28.73","StandardCNY":"43.12","PremiumCNY":"57.52","Code":"HT","Translation":"海地"},{"Country":"Jamaica","Currency":"USD","Mobile":"","Standard with ads":"","Basic":"3.99","Standard":"5.99","Premium":"7.99","Extra member slots":"Standard: 2.99 / Premium: 2.99","MobileUSD":"","With_Ads_USD":"","BasicUSD":"3.99","StandardUSD":"5.99","PremiumUSD":"7.99","MobileCNY":"","With_Ads_CNY":"","BasicCNY":"28.73","StandardCNY":"43.12","PremiumCNY":"57.52","Code":"JM","Translation":"牙买加"},{"Country":"Nicaragua","Currency":"USD","Mobile":"","Standard with ads":"","Basic":"3.99","Standard":"5.99","Premium":"7.99","Extra member slots":"Standard: 2.99 / Premium: 2.99","MobileUSD":"","With_Ads_USD":"","BasicUSD":"3.99","StandardUSD":"5.99","PremiumUSD":"7.99","MobileCNY":"","With_Ads_CNY":"","BasicCNY":"28.73","StandardCNY":"43.12","PremiumCNY":"57.52","Code":"NI","Translation":"尼加拉瓜"},{"Country":"Paraguay","Currency":"USD","Mobile":"","Standard with ads":"","Basic":"3.99","Standard":"5.99","Premium":"7.99","Extra member slots":"Standard: 2.99 / Premium: 2.99","MobileUSD":"","With_Ads_USD":"","BasicUSD":"3.99","StandardUSD":"5.99","PremiumUSD":"7.99","MobileCNY":"","With_Ads_CNY":"","BasicCNY":"28.73","StandardCNY":"43.12","PremiumCNY":"57.52","Code":"PY","Translation":"巴拉圭"},{"Country":"St. Barthélemy","Currency":"USD","Mobile":"","Standard with ads":"","Basic":"3.99","Standard":"5.99","Premium":"7.99","Extra member slots":"Standard: 2.99 / Premium: 2.99","MobileUSD":"","With_Ads_USD":"","BasicUSD":"3.99","StandardUSD":"5.99","PremiumUSD":"7.99","MobileCNY":"","With_Ads_CNY":"","BasicCNY":"28.73","StandardCNY":"43.12","PremiumCNY":"57.52","Code":"BL","Translation":"英石。巴塞洛缪"},{"Country":"St. Lucia","Currency":"USD","Mobile":"","Standard with ads":"","Basic":"3.99","Standard":"5.99","Premium":"7.99","Extra member slots":"Standard: 2.99 / Premium: 2.99","MobileUSD":"","With_Ads_USD":"","BasicUSD":"3.99","StandardUSD":"5.99","PremiumUSD":"7.99","MobileCNY":"","With_Ads_CNY":"","BasicCNY":"28.73","StandardCNY":"43.12","PremiumCNY":"57.52","Code":"LC","Translation":"英石。露西娅"},{"Country":"St. Martin","Currency":"USD","Mobile":"","Standard with ads":"","Basic":"3.99","Standard":"5.99","Premium":"7.99","Extra member slots":"Standard: 2.99 / Premium: 2.99","MobileUSD":"","With_Ads_USD":"","BasicUSD":"3.99","StandardUSD":"5.99","PremiumUSD":"7.99","MobileCNY":"","With_Ads_CNY":"","BasicCNY":"28.73","StandardCNY":"43.12","PremiumCNY":"57.52","Code":"MF","Translation":"圣马丁"},{"Country":"St. Vincent & Grenadines","Currency":"USD","Mobile":"","Standard with ads":"","Basic":"3.99","Standard":"5.99","Premium":"7.99","Extra member slots":"Standard: 2.99 / Premium: 2.99","MobileUSD":"","With_Ads_USD":"","BasicUSD":"3.99","StandardUSD":"5.99","PremiumUSD":"7.99","MobileCNY":"","With_Ads_CNY":"","BasicCNY":"28.73","StandardCNY":"43.12","PremiumCNY":"57.52","Code":"VC","Translation":"圣文森特和格林纳丁斯"},{"Country":"Suriname","Currency":"USD","Mobile":"","Standard with ads":"","Basic":"3.99","Standard":"5.99","Premium":"7.99","Extra member slots":"Standard: 2.99 / Premium: 2.99","MobileUSD":"","With_Ads_USD":"","BasicUSD":"3.99","StandardUSD":"5.99","PremiumUSD":"7.99","MobileCNY":"","With_Ads_CNY":"","BasicCNY":"28.73","StandardCNY":"43.12","PremiumCNY":"57.52","Code":"SR","Translation":"苏里南"},{"Country":"Venezuela","Currency":"USD","Mobile":"","Standard with ads":"","Basic":"3.99","Standard":"5.99","Premium":"7.99","Extra member slots":"Standard: 2.99 / Premium: 2.99","MobileUSD":"","With_Ads_USD":"","BasicUSD":"3.99","StandardUSD":"5.99","PremiumUSD":"7.99","MobileCNY":"","With_Ads_CNY":"","BasicCNY":"28.73","StandardCNY":"43.12","PremiumCNY":"57.52","Code":"VE","Translation":"委内瑞拉"},{"Country":"Kenya","Currency":"KES","Mobile":"200","Standard with ads":"","Basic":"300","Standard":"700","Premium":"1100","Extra member slots":"","MobileUSD":"1.51","With_Ads_USD":"","BasicUSD":"2.26","StandardUSD":"5.27","PremiumUSD":"8.29","MobileCNY":"10.85","With_Ads_CNY":"","BasicCNY":"16.27","StandardCNY":"37.96","PremiumCNY":"59.66","Code":"KE","Translation":"肯尼亚"},{"Country":"Morocco","Currency":"MAD","Mobile":"","Standard with ads":"","Basic":"35","Standard":"65","Premium":"95","Extra member slots":"","MobileUSD":"","With_Ads_USD":"","BasicUSD":"3.51","StandardUSD":"6.52","PremiumUSD":"9.53","MobileCNY":"","With_Ads_CNY":"","BasicCNY":"25.31","StandardCNY":"47.01","PremiumCNY":"68.70","Code":"MA","Translation":"摩洛哥"},{"Country":"Philippines","Currency":"PHP","Mobile":"149","Standard with ads":"","Basic":"249","Standard":"399","Premium":"549","Extra member slots":"Standard: 149 / Premium: 149","MobileUSD":"2.66","With_Ads_USD":"","BasicUSD":"4.44","StandardUSD":"7.12","PremiumUSD":"9.79","MobileCNY":"19.13","With_Ads_CNY":"","BasicCNY":"31.97","StandardCNY":"51.23","PremiumCNY":"70.49","Code":"PH","Translation":"菲律宾"},{"Country":"Afghanistan","Currency":"USD","Mobile":"","Standard with ads":"","Basic":"3.99","Standard":"7.99","Premium":"9.99","Extra member slots":"","MobileUSD":"","With_Ads_USD":"","BasicUSD":"3.99","StandardUSD":"7.99","PremiumUSD":"9.99","MobileCNY":"","With_Ads_CNY":"","BasicCNY":"28.73","StandardCNY":"57.52","PremiumCNY":"71.92","Code":"AF","Translation":"阿富汗"},{"Country":"Algeria","Currency":"USD","Mobile":"","Standard with ads":"","Basic":"3.99","Standard":"7.99","Premium":"9.99","Extra member slots":"","MobileUSD":"","With_Ads_USD":"","BasicUSD":"3.99","StandardUSD":"7.99","PremiumUSD":"9.99","MobileCNY":"","With_Ads_CNY":"","BasicCNY":"28.73","StandardCNY":"57.52","PremiumCNY":"71.92","Code":"DZ","Translation":"阿尔及利亚"},{"Country":"Angola","Currency":"USD","Mobile":"2.99","Standard with ads":"","Basic":"3.99","Standard":"7.99","Premium":"9.99","Extra member slots":"","MobileUSD":"2.99","With_Ads_USD":"","BasicUSD":"3.99","StandardUSD":"7.99","PremiumUSD":"9.99","MobileCNY":"21.53","With_Ads_CNY":"","BasicCNY":"28.73","StandardCNY":"57.52","PremiumCNY":"71.92","Code":"AO","Translation":"安哥拉"},{"Country":"Bangladesh","Currency":"USD","Mobile":"2.99","Standard with ads":"","Basic":"3.99","Standard":"7.99","Premium":"9.99","Extra member slots":"","MobileUSD":"2.99","With_Ads_USD":"","BasicUSD":"3.99","StandardUSD":"7.99","PremiumUSD":"9.99","MobileCNY":"21.53","With_Ads_CNY":"","BasicCNY":"28.73","StandardCNY":"57.52","PremiumCNY":"71.92","Code":"BD","Translation":"孟加拉国"},{"Country":"Benin","Currency":"USD","Mobile":"2.99","Standard with ads":"","Basic":"3.99","Standard":"7.99","Premium":"9.99","Extra member slots":"","MobileUSD":"2.99","With_Ads_USD":"","BasicUSD":"3.99","StandardUSD":"7.99","PremiumUSD":"9.99","MobileCNY":"21.53","With_Ads_CNY":"","BasicCNY":"28.73","StandardCNY":"57.52","PremiumCNY":"71.92","Code":"BJ","Translation":"贝宁"},{"Country":"Bhutan","Currency":"USD","Mobile":"2.99","Standard with ads":"","Basic":"3.99","Standard":"7.99","Premium":"9.99","Extra member slots":"","MobileUSD":"2.99","With_Ads_USD":"","BasicUSD":"3.99","StandardUSD":"7.99","PremiumUSD":"9.99","MobileCNY":"21.53","With_Ads_CNY":"","BasicCNY":"28.73","StandardCNY":"57.52","PremiumCNY":"71.92","Code":"BT","Translation":"不丹"},{"Country":"Botswana","Currency":"USD","Mobile":"2.99","Standard with ads":"","Basic":"3.99","Standard":"7.99","Premium":"9.99","Extra member slots":"","MobileUSD":"2.99","With_Ads_USD":"","BasicUSD":"3.99","StandardUSD":"7.99","PremiumUSD":"9.99","MobileCNY":"21.53","With_Ads_CNY":"","BasicCNY":"28.73","StandardCNY":"57.52","PremiumCNY":"71.92","Code":"BW","Translation":"博茨瓦纳"},{"Country":"British Indian Ocean Territory","Currency":"USD","Mobile":"2.99","Standard with ads":"","Basic":"3.99","Standard":"7.99","Premium":"9.99","Extra member slots":"","MobileUSD":"2.99","With_Ads_USD":"","BasicUSD":"3.99","StandardUSD":"7.99","PremiumUSD":"9.99","MobileCNY":"21.53","With_Ads_CNY":"","BasicCNY":"28.73","StandardCNY":"57.52","PremiumCNY":"71.92","Code":"IO","Translation":"英属印度洋领地"},{"Country":"Burkina Faso","Currency":"USD","Mobile":"2.99","Standard with ads":"","Basic":"3.99","Standard":"7.99","Premium":"9.99","Extra member slots":"","MobileUSD":"2.99","With_Ads_USD":"","BasicUSD":"3.99","StandardUSD":"7.99","PremiumUSD":"9.99","MobileCNY":"21.53","With_Ads_CNY":"","BasicCNY":"28.73","StandardCNY":"57.52","PremiumCNY":"71.92","Code":"BF","Translation":"布基纳法索"},{"Country":"Burundi","Currency":"USD","Mobile":"2.99","Standard with ads":"","Basic":"3.99","Standard":"7.99","Premium":"9.99","Extra member slots":"","MobileUSD":"2.99","With_Ads_USD":"","BasicUSD":"3.99","StandardUSD":"7.99","PremiumUSD":"9.99","MobileCNY":"21.53","With_Ads_CNY":"","BasicCNY":"28.73","StandardCNY":"57.52","PremiumCNY":"71.92","Code":"BI","Translation":"布隆迪"},{"Country":"Cambodia","Currency":"USD","Mobile":"2.99","Standard with ads":"","Basic":"3.99","Standard":"7.99","Premium":"9.99","Extra member slots":"","MobileUSD":"2.99","With_Ads_USD":"","BasicUSD":"3.99","StandardUSD":"7.99","PremiumUSD":"9.99","MobileCNY":"21.53","With_Ads_CNY":"","BasicCNY":"28.73","StandardCNY":"57.52","PremiumCNY":"71.92","Code":"KH","Translation":"柬埔寨"},{"Country":"Cameroon","Currency":"USD","Mobile":"2.99","Standard with ads":"","Basic":"3.99","Standard":"7.99","Premium":"9.99","Extra member slots":"","MobileUSD":"2.99","With_Ads_USD":"","BasicUSD":"3.99","StandardUSD":"7.99","PremiumUSD":"9.99","MobileCNY":"21.53","With_Ads_CNY":"","BasicCNY":"28.73","StandardCNY":"57.52","PremiumCNY":"71.92","Code":"CM","Translation":"喀麦隆"},{"Country":"Cape Verde","Currency":"USD","Mobile":"2.99","Standard with ads":"","Basic":"3.99","Standard":"7.99","Premium":"9.99","Extra member slots":"","MobileUSD":"2.99","With_Ads_USD":"","BasicUSD":"3.99","StandardUSD":"7.99","PremiumUSD":"9.99","MobileCNY":"21.53","With_Ads_CNY":"","BasicCNY":"28.73","StandardCNY":"57.52","PremiumCNY":"71.92","Code":"CV","Translation":"佛得角"},{"Country":"Central African Republic","Currency":"USD","Mobile":"2.99","Standard with ads":"","Basic":"3.99","Standard":"7.99","Premium":"9.99","Extra member slots":"","MobileUSD":"2.99","With_Ads_USD":"","BasicUSD":"3.99","StandardUSD":"7.99","PremiumUSD":"9.99","MobileCNY":"21.53","With_Ads_CNY":"","BasicCNY":"28.73","StandardCNY":"57.52","PremiumCNY":"71.92","Code":"CF","Translation":"中非共和国"},{"Country":"Chad","Currency":"USD","Mobile":"2.99","Standard with ads":"","Basic":"3.99","Standard":"7.99","Premium":"9.99","Extra member slots":"","MobileUSD":"2.99","With_Ads_USD":"","BasicUSD":"3.99","StandardUSD":"7.99","PremiumUSD":"9.99","MobileCNY":"21.53","With_Ads_CNY":"","BasicCNY":"28.73","StandardCNY":"57.52","PremiumCNY":"71.92","Code":"TD","Translation":"乍得"},{"Country":"Christmas Island","Currency":"USD","Mobile":"","Standard with ads":"","Basic":"3.99","Standard":"7.99","Premium":"9.99","Extra member slots":"","MobileUSD":"","With_Ads_USD":"","BasicUSD":"3.99","StandardUSD":"7.99","PremiumUSD":"9.99","MobileCNY":"","With_Ads_CNY":"","BasicCNY":"28.73","StandardCNY":"57.52","PremiumCNY":"71.92","Code":"CX","Translation":"圣诞岛"},{"Country":"Comoros","Currency":"USD","Mobile":"2.99","Standard with ads":"","Basic":"3.99","Standard":"7.99","Premium":"9.99","Extra member slots":"","MobileUSD":"2.99","With_Ads_USD":"","BasicUSD":"3.99","StandardUSD":"7.99","PremiumUSD":"9.99","MobileCNY":"21.53","With_Ads_CNY":"","BasicCNY":"28.73","StandardCNY":"57.52","PremiumCNY":"71.92","Code":"KM","Translation":"科摩罗"},{"Country":"Congo - Brazzaville","Currency":"USD","Mobile":"2.99","Standard with ads":"","Basic":"3.99","Standard":"7.99","Premium":"9.99","Extra member slots":"","MobileUSD":"2.99","With_Ads_USD":"","BasicUSD":"3.99","StandardUSD":"7.99","PremiumUSD":"9.99","MobileCNY":"21.53","With_Ads_CNY":"","BasicCNY":"28.73","StandardCNY":"57.52","PremiumCNY":"71.92","Code":"CG","Translation":"刚果 - 布拉柴维尔"},{"Country":"Congo - Kinshasa","Currency":"USD","Mobile":"2.99","Standard with ads":"","Basic":"3.99","Standard":"7.99","Premium":"9.99","Extra member slots":"","MobileUSD":"2.99","With_Ads_USD":"","BasicUSD":"3.99","StandardUSD":"7.99","PremiumUSD":"9.99","MobileCNY":"21.53","With_Ads_CNY":"","BasicCNY":"28.73","StandardCNY":"57.52","PremiumCNY":"71.92","Code":"CD","Translation":"刚果 - 金沙萨"},{"Country":"Côte d’Ivoire","Currency":"USD","Mobile":"2.99","Standard with ads":"","Basic":"3.99","Standard":"7.99","Premium":"9.99","Extra member slots":"","MobileUSD":"2.99","With_Ads_USD":"","BasicUSD":"3.99","StandardUSD":"7.99","PremiumUSD":"9.99","MobileCNY":"21.53","With_Ads_CNY":"","BasicCNY":"28.73","StandardCNY":"57.52","PremiumCNY":"71.92","Code":"CI","Translation":"象牙海岸"},{"Country":"Djibouti","Currency":"USD","Mobile":"2.99","Standard with ads":"","Basic":"3.99","Standard":"7.99","Premium":"9.99","Extra member slots":"","MobileUSD":"2.99","With_Ads_USD":"","BasicUSD":"3.99","StandardUSD":"7.99","PremiumUSD":"9.99","MobileCNY":"21.53","With_Ads_CNY":"","BasicCNY":"28.73","StandardCNY":"57.52","PremiumCNY":"71.92","Code":"DJ","Translation":"吉布提"},{"Country":"Equatorial Guinea","Currency":"USD","Mobile":"2.99","Standard with ads":"","Basic":"3.99","Standard":"7.99","Premium":"9.99","Extra member slots":"","MobileUSD":"2.99","With_Ads_USD":"","BasicUSD":"3.99","StandardUSD":"7.99","PremiumUSD":"9.99","MobileCNY":"21.53","With_Ads_CNY":"","BasicCNY":"28.73","StandardCNY":"57.52","PremiumCNY":"71.92","Code":"GQ","Translation":"赤道几内亚"},{"Country":"Eritrea","Currency":"USD","Mobile":"2.99","Standard with ads":"","Basic":"3.99","Standard":"7.99","Premium":"9.99","Extra member slots":"","MobileUSD":"2.99","With_Ads_USD":"","BasicUSD":"3.99","StandardUSD":"7.99","PremiumUSD":"9.99","MobileCNY":"21.53","With_Ads_CNY":"","BasicCNY":"28.73","StandardCNY":"57.52","PremiumCNY":"71.92","Code":"ER","Translation":"厄立特里亚"},{"Country":"Eswatini","Currency":"USD","Mobile":"2.99","Standard with ads":"","Basic":"3.99","Standard":"7.99","Premium":"9.99","Extra member slots":"","MobileUSD":"2.99","With_Ads_USD":"","BasicUSD":"3.99","StandardUSD":"7.99","PremiumUSD":"9.99","MobileCNY":"21.53","With_Ads_CNY":"","BasicCNY":"28.73","StandardCNY":"57.52","PremiumCNY":"71.92","Code":"SZ","Translation":"在斯瓦特"},{"Country":"Ethiopia","Currency":"USD","Mobile":"2.99","Standard with ads":"","Basic":"3.99","Standard":"7.99","Premium":"9.99","Extra member slots":"","MobileUSD":"2.99","With_Ads_USD":"","BasicUSD":"3.99","StandardUSD":"7.99","PremiumUSD":"9.99","MobileCNY":"21.53","With_Ads_CNY":"","BasicCNY":"28.73","StandardCNY":"57.52","PremiumCNY":"71.92","Code":"ET","Translation":"埃塞俄比亚"},{"Country":"Fiji","Currency":"USD","Mobile":"2.99","Standard with ads":"","Basic":"3.99","Standard":"7.99","Premium":"9.99","Extra member slots":"","MobileUSD":"2.99","With_Ads_USD":"","BasicUSD":"3.99","StandardUSD":"7.99","PremiumUSD":"9.99","MobileCNY":"21.53","With_Ads_CNY":"","BasicCNY":"28.73","StandardCNY":"57.52","PremiumCNY":"71.92","Code":"FJ","Translation":"斐济"},{"Country":"Gabon","Currency":"USD","Mobile":"2.99","Standard with ads":"","Basic":"3.99","Standard":"7.99","Premium":"9.99","Extra member slots":"","MobileUSD":"2.99","With_Ads_USD":"","BasicUSD":"3.99","StandardUSD":"7.99","PremiumUSD":"9.99","MobileCNY":"21.53","With_Ads_CNY":"","BasicCNY":"28.73","StandardCNY":"57.52","PremiumCNY":"71.92","Code":"GA","Translation":"加蓬"},{"Country":"Gambia","Currency":"USD","Mobile":"2.99","Standard with ads":"","Basic":"3.99","Standard":"7.99","Premium":"9.99","Extra member slots":"","MobileUSD":"2.99","With_Ads_USD":"","BasicUSD":"3.99","StandardUSD":"7.99","PremiumUSD":"9.99","MobileCNY":"21.53","With_Ads_CNY":"","BasicCNY":"28.73","StandardCNY":"57.52","PremiumCNY":"71.92","Code":"GM","Translation":"冈比亚"},{"Country":"Ghana","Currency":"USD","Mobile":"2.99","Standard with ads":"","Basic":"3.99","Standard":"7.99","Premium":"9.99","Extra member slots":"","MobileUSD":"2.99","With_Ads_USD":"","BasicUSD":"3.99","StandardUSD":"7.99","PremiumUSD":"9.99","MobileCNY":"21.53","With_Ads_CNY":"","BasicCNY":"28.73","StandardCNY":"57.52","PremiumCNY":"71.92","Code":"GH","Translation":"加纳"},{"Country":"Guinea","Currency":"USD","Mobile":"2.99","Standard with ads":"","Basic":"3.99","Standard":"7.99","Premium":"9.99","Extra member slots":"","MobileUSD":"2.99","With_Ads_USD":"","BasicUSD":"3.99","StandardUSD":"7.99","PremiumUSD":"9.99","MobileCNY":"21.53","With_Ads_CNY":"","BasicCNY":"28.73","StandardCNY":"57.52","PremiumCNY":"71.92","Code":"GN","Translation":"几内亚"},{"Country":"Guinea-Bissau","Currency":"USD","Mobile":"2.99","Standard with ads":"","Basic":"3.99","Standard":"7.99","Premium":"9.99","Extra member slots":"","MobileUSD":"2.99","With_Ads_USD":"","BasicUSD":"3.99","StandardUSD":"7.99","PremiumUSD":"9.99","MobileCNY":"21.53","With_Ads_CNY":"","BasicCNY":"28.73","StandardCNY":"57.52","PremiumCNY":"71.92","Code":"GW","Translation":"几内亚比绍"},{"Country":"Iraq","Currency":"USD","Mobile":"","Standard with ads":"","Basic":"3.99","Standard":"7.99","Premium":"9.99","Extra member slots":"","MobileUSD":"","With_Ads_USD":"","BasicUSD":"3.99","StandardUSD":"7.99","PremiumUSD":"9.99","MobileCNY":"","With_Ads_CNY":"","BasicCNY":"28.73","StandardCNY":"57.52","PremiumCNY":"71.92","Code":"IQ","Translation":"伊拉克"},{"Country":"Jordan","Currency":"USD","Mobile":"","Standard with ads":"","Basic":"3.99","Standard":"7.99","Premium":"9.99","Extra member slots":"","MobileUSD":"","With_Ads_USD":"","BasicUSD":"3.99","StandardUSD":"7.99","PremiumUSD":"9.99","MobileCNY":"","With_Ads_CNY":"","BasicCNY":"28.73","StandardCNY":"57.52","PremiumCNY":"71.92","Code":"JO","Translation":"约旦"},{"Country":"Kiribati","Currency":"USD","Mobile":"2.99","Standard with ads":"","Basic":"3.99","Standard":"7.99","Premium":"9.99","Extra member slots":"","MobileUSD":"2.99","With_Ads_USD":"","BasicUSD":"3.99","StandardUSD":"7.99","PremiumUSD":"9.99","MobileCNY":"21.53","With_Ads_CNY":"","BasicCNY":"28.73","StandardCNY":"57.52","PremiumCNY":"71.92","Code":"KI","Translation":"基里巴斯"},{"Country":"Laos","Currency":"USD","Mobile":"2.99","Standard with ads":"","Basic":"3.99","Standard":"7.99","Premium":"9.99","Extra member slots":"","MobileUSD":"2.99","With_Ads_USD":"","BasicUSD":"3.99","StandardUSD":"7.99","PremiumUSD":"9.99","MobileCNY":"21.53","With_Ads_CNY":"","BasicCNY":"28.73","StandardCNY":"57.52","PremiumCNY":"71.92","Code":"LA","Translation":"老挝"},{"Country":"Lebanon","Currency":"USD","Mobile":"","Standard with ads":"","Basic":"3.99","Standard":"7.99","Premium":"9.99","Extra member slots":"","MobileUSD":"","With_Ads_USD":"","BasicUSD":"3.99","StandardUSD":"7.99","PremiumUSD":"9.99","MobileCNY":"","With_Ads_CNY":"","BasicCNY":"28.73","StandardCNY":"57.52","PremiumCNY":"71.92","Code":"LB","Translation":"黎巴嫩"},{"Country":"Lesotho","Currency":"USD","Mobile":"2.99","Standard with ads":"","Basic":"3.99","Standard":"7.99","Premium":"9.99","Extra member slots":"","MobileUSD":"2.99","With_Ads_USD":"","BasicUSD":"3.99","StandardUSD":"7.99","PremiumUSD":"9.99","MobileCNY":"21.53","With_Ads_CNY":"","BasicCNY":"28.73","StandardCNY":"57.52","PremiumCNY":"71.92","Code":"LS","Translation":"莱索托"},{"Country":"Liberia","Currency":"USD","Mobile":"2.99","Standard with ads":"","Basic":"3.99","Standard":"7.99","Premium":"9.99","Extra member slots":"","MobileUSD":"2.99","With_Ads_USD":"","BasicUSD":"3.99","StandardUSD":"7.99","PremiumUSD":"9.99","MobileCNY":"21.53","With_Ads_CNY":"","BasicCNY":"28.73","StandardCNY":"57.52","PremiumCNY":"71.92","Code":"LR","Translation":"利比里亚"},{"Country":"Libya","Currency":"USD","Mobile":"","Standard with ads":"","Basic":"3.99","Standard":"7.99","Premium":"9.99","Extra member slots":"","MobileUSD":"","With_Ads_USD":"","BasicUSD":"3.99","StandardUSD":"7.99","PremiumUSD":"9.99","MobileCNY":"","With_Ads_CNY":"","BasicCNY":"28.73","StandardCNY":"57.52","PremiumCNY":"71.92","Code":"LY","Translation":"利比亚"},{"Country":"Madagascar","Currency":"USD","Mobile":"2.99","Standard with ads":"","Basic":"3.99","Standard":"7.99","Premium":"9.99","Extra member slots":"","MobileUSD":"2.99","With_Ads_USD":"","BasicUSD":"3.99","StandardUSD":"7.99","PremiumUSD":"9.99","MobileCNY":"21.53","With_Ads_CNY":"","BasicCNY":"28.73","StandardCNY":"57.52","PremiumCNY":"71.92","Code":"MG","Translation":"马达加斯加"},{"Country":"Malawi","Currency":"USD","Mobile":"2.99","Standard with ads":"","Basic":"3.99","Standard":"7.99","Premium":"9.99","Extra member slots":"","MobileUSD":"2.99","With_Ads_USD":"","BasicUSD":"3.99","StandardUSD":"7.99","PremiumUSD":"9.99","MobileCNY":"21.53","With_Ads_CNY":"","BasicCNY":"28.73","StandardCNY":"57.52","PremiumCNY":"71.92","Code":"MW","Translation":"马拉维"},{"Country":"Mali","Currency":"USD","Mobile":"2.99","Standard with ads":"","Basic":"3.99","Standard":"7.99","Premium":"9.99","Extra member slots":"","MobileUSD":"2.99","With_Ads_USD":"","BasicUSD":"3.99","StandardUSD":"7.99","PremiumUSD":"9.99","MobileCNY":"21.53","With_Ads_CNY":"","BasicCNY":"28.73","StandardCNY":"57.52","PremiumCNY":"71.92","Code":"ML","Translation":"他们有"},{"Country":"Mauritania","Currency":"USD","Mobile":"2.99","Standard with ads":"","Basic":"3.99","Standard":"7.99","Premium":"9.99","Extra member slots":"","MobileUSD":"2.99","With_Ads_USD":"","BasicUSD":"3.99","StandardUSD":"7.99","PremiumUSD":"9.99","MobileCNY":"21.53","With_Ads_CNY":"","BasicCNY":"28.73","StandardCNY":"57.52","PremiumCNY":"71.92","Code":"MR","Translation":"毛里塔尼亚"},{"Country":"Mauritius","Currency":"USD","Mobile":"2.99","Standard with ads":"","Basic":"3.99","Standard":"7.99","Premium":"9.99","Extra member slots":"","MobileUSD":"2.99","With_Ads_USD":"","BasicUSD":"3.99","StandardUSD":"7.99","PremiumUSD":"9.99","MobileCNY":"21.53","With_Ads_CNY":"","BasicCNY":"28.73","StandardCNY":"57.52","PremiumCNY":"71.92","Code":"MU","Translation":"毛里求斯"},{"Country":"Mongolia","Currency":"USD","Mobile":"2.99","Standard with ads":"","Basic":"3.99","Standard":"7.99","Premium":"9.99","Extra member slots":"","MobileUSD":"2.99","With_Ads_USD":"","BasicUSD":"3.99","StandardUSD":"7.99","PremiumUSD":"9.99","MobileCNY":"21.53","With_Ads_CNY":"","BasicCNY":"28.73","StandardCNY":"57.52","PremiumCNY":"71.92","Code":"MN","Translation":"蒙古"},{"Country":"Mozambique","Currency":"USD","Mobile":"2.99","Standard with ads":"","Basic":"3.99","Standard":"7.99","Premium":"9.99","Extra member slots":"","MobileUSD":"2.99","With_Ads_USD":"","BasicUSD":"3.99","StandardUSD":"7.99","PremiumUSD":"9.99","MobileCNY":"21.53","With_Ads_CNY":"","BasicCNY":"28.73","StandardCNY":"57.52","PremiumCNY":"71.92","Code":"MZ","Translation":"莫桑比克"},{"Country":"Myanmar (Burma)","Currency":"USD","Mobile":"2.99","Standard with ads":"","Basic":"3.99","Standard":"7.99","Premium":"9.99","Extra member slots":"","MobileUSD":"2.99","With_Ads_USD":"","BasicUSD":"3.99","StandardUSD":"7.99","PremiumUSD":"9.99","MobileCNY":"21.53","With_Ads_CNY":"","BasicCNY":"28.73","StandardCNY":"57.52","PremiumCNY":"71.92","Code":"MM","Translation":"缅甸（缅甸）"},{"Country":"Namibia","Currency":"USD","Mobile":"2.99","Standard with ads":"","Basic":"3.99","Standard":"7.99","Premium":"9.99","Extra member slots":"","MobileUSD":"2.99","With_Ads_USD":"","BasicUSD":"3.99","StandardUSD":"7.99","PremiumUSD":"9.99","MobileCNY":"21.53","With_Ads_CNY":"","BasicCNY":"28.73","StandardCNY":"57.52","PremiumCNY":"71.92","Code":"NA","Translation":"纳米比亚"},{"Country":"Nepal","Currency":"USD","Mobile":"2.99","Standard with ads":"","Basic":"3.99","Standard":"7.99","Premium":"9.99","Extra member slots":"","MobileUSD":"2.99","With_Ads_USD":"","BasicUSD":"3.99","StandardUSD":"7.99","PremiumUSD":"9.99","MobileCNY":"21.53","With_Ads_CNY":"","BasicCNY":"28.73","StandardCNY":"57.52","PremiumCNY":"71.92","Code":"NP","Translation":"尼泊尔"},{"Country":"Niger","Currency":"USD","Mobile":"2.99","Standard with ads":"","Basic":"3.99","Standard":"7.99","Premium":"9.99","Extra member slots":"","MobileUSD":"2.99","With_Ads_USD":"","BasicUSD":"3.99","StandardUSD":"7.99","PremiumUSD":"9.99","MobileCNY":"21.53","With_Ads_CNY":"","BasicCNY":"28.73","StandardCNY":"57.52","PremiumCNY":"71.92","Code":"NE","Translation":"尼日尔"},{"Country":"Palestine","Currency":"USD","Mobile":"","Standard with ads":"","Basic":"3.99","Standard":"7.99","Premium":"9.99","Extra member slots":"","MobileUSD":"","With_Ads_USD":"","BasicUSD":"3.99","StandardUSD":"7.99","PremiumUSD":"9.99","MobileCNY":"","With_Ads_CNY":"","BasicCNY":"28.73","StandardCNY":"57.52","PremiumCNY":"71.92","Code":"PS","Translation":"巴勒斯坦"},{"Country":"Papua New Guinea","Currency":"USD","Mobile":"2.99","Standard with ads":"","Basic":"3.99","Standard":"7.99","Premium":"9.99","Extra member slots":"","MobileUSD":"2.99","With_Ads_USD":"","BasicUSD":"3.99","StandardUSD":"7.99","PremiumUSD":"9.99","MobileCNY":"21.53","With_Ads_CNY":"","BasicCNY":"28.73","StandardCNY":"57.52","PremiumCNY":"71.92","Code":"PG","Translation":"巴布亚新几内亚"},{"Country":"Pitcairn Islands","Currency":"USD","Mobile":"2.99","Standard with ads":"","Basic":"3.99","Standard":"7.99","Premium":"9.99","Extra member slots":"","MobileUSD":"2.99","With_Ads_USD":"","BasicUSD":"3.99","StandardUSD":"7.99","PremiumUSD":"9.99","MobileCNY":"21.53","With_Ads_CNY":"","BasicCNY":"28.73","StandardCNY":"57.52","PremiumCNY":"71.92","Code":"PN","Translation":"皮特凯恩群岛"},{"Country":"Rwanda","Currency":"USD","Mobile":"2.99","Standard with ads":"","Basic":"3.99","Standard":"7.99","Premium":"9.99","Extra member slots":"","MobileUSD":"2.99","With_Ads_USD":"","BasicUSD":"3.99","StandardUSD":"7.99","PremiumUSD":"9.99","MobileCNY":"21.53","With_Ads_CNY":"","BasicCNY":"28.73","StandardCNY":"57.52","PremiumCNY":"71.92","Code":"RW","Translation":"卢旺达"},{"Country":"Samoa","Currency":"USD","Mobile":"2.99","Standard with ads":"","Basic":"3.99","Standard":"7.99","Premium":"9.99","Extra member slots":"","MobileUSD":"2.99","With_Ads_USD":"","BasicUSD":"3.99","StandardUSD":"7.99","PremiumUSD":"9.99","MobileCNY":"21.53","With_Ads_CNY":"","BasicCNY":"28.73","StandardCNY":"57.52","PremiumCNY":"71.92","Code":"WS","Translation":"萨摩亚"},{"Country":"São Tomé & Príncipe","Currency":"USD","Mobile":"2.99","Standard with ads":"","Basic":"3.99","Standard":"7.99","Premium":"9.99","Extra member slots":"","MobileUSD":"2.99","With_Ads_USD":"","BasicUSD":"3.99","StandardUSD":"7.99","PremiumUSD":"9.99","MobileCNY":"21.53","With_Ads_CNY":"","BasicCNY":"28.73","StandardCNY":"57.52","PremiumCNY":"71.92","Code":"ST","Translation":"圣多美和普林西比"},{"Country":"Senegal","Currency":"USD","Mobile":"2.99","Standard with ads":"","Basic":"3.99","Standard":"7.99","Premium":"9.99","Extra member slots":"","MobileUSD":"2.99","With_Ads_USD":"","BasicUSD":"3.99","StandardUSD":"7.99","PremiumUSD":"9.99","MobileCNY":"21.53","With_Ads_CNY":"","BasicCNY":"28.73","StandardCNY":"57.52","PremiumCNY":"71.92","Code":"SN","Translation":"塞内加尔"},{"Country":"Seychelles","Currency":"USD","Mobile":"2.99","Standard with ads":"","Basic":"3.99","Standard":"7.99","Premium":"9.99","Extra member slots":"","MobileUSD":"2.99","With_Ads_USD":"","BasicUSD":"3.99","StandardUSD":"7.99","PremiumUSD":"9.99","MobileCNY":"21.53","With_Ads_CNY":"","BasicCNY":"28.73","StandardCNY":"57.52","PremiumCNY":"71.92","Code":"SC","Translation":"塞舌尔"},{"Country":"Sierra Leone","Currency":"USD","Mobile":"2.99","Standard with ads":"","Basic":"3.99","Standard":"7.99","Premium":"9.99","Extra member slots":"","MobileUSD":"2.99","With_Ads_USD":"","BasicUSD":"3.99","StandardUSD":"7.99","PremiumUSD":"9.99","MobileCNY":"21.53","With_Ads_CNY":"","BasicCNY":"28.73","StandardCNY":"57.52","PremiumCNY":"71.92","Code":"SL","Translation":"塞拉利昂"},{"Country":"Solomon Islands","Currency":"USD","Mobile":"2.99","Standard with ads":"","Basic":"3.99","Standard":"7.99","Premium":"9.99","Extra member slots":"","MobileUSD":"2.99","With_Ads_USD":"","BasicUSD":"3.99","StandardUSD":"7.99","PremiumUSD":"9.99","MobileCNY":"21.53","With_Ads_CNY":"","BasicCNY":"28.73","StandardCNY":"57.52","PremiumCNY":"71.92","Code":"SB","Translation":"所罗门群岛"},{"Country":"Somalia","Currency":"USD","Mobile":"2.99","Standard with ads":"","Basic":"3.99","Standard":"7.99","Premium":"9.99","Extra member slots":"","MobileUSD":"2.99","With_Ads_USD":"","BasicUSD":"3.99","StandardUSD":"7.99","PremiumUSD":"9.99","MobileCNY":"21.53","With_Ads_CNY":"","BasicCNY":"28.73","StandardCNY":"57.52","PremiumCNY":"71.92","Code":"SO","Translation":"索马里"},{"Country":"South Sudan","Currency":"USD","Mobile":"2.99","Standard with ads":"","Basic":"3.99","Standard":"7.99","Premium":"9.99","Extra member slots":"","MobileUSD":"2.99","With_Ads_USD":"","BasicUSD":"3.99","StandardUSD":"7.99","PremiumUSD":"9.99","MobileCNY":"21.53","With_Ads_CNY":"","BasicCNY":"28.73","StandardCNY":"57.52","PremiumCNY":"71.92","Code":"SS","Translation":"南苏丹"},{"Country":"Sri Lanka","Currency":"USD","Mobile":"2.99","Standard with ads":"","Basic":"3.99","Standard":"7.99","Premium":"9.99","Extra member slots":"","MobileUSD":"2.99","With_Ads_USD":"","BasicUSD":"3.99","StandardUSD":"7.99","PremiumUSD":"9.99","MobileCNY":"21.53","With_Ads_CNY":"","BasicCNY":"28.73","StandardCNY":"57.52","PremiumCNY":"71.92","Code":"LK","Translation":"斯里兰卡"},{"Country":"St. Helena","Currency":"USD","Mobile":"2.99","Standard with ads":"","Basic":"3.99","Standard":"7.99","Premium":"9.99","Extra member slots":"","MobileUSD":"2.99","With_Ads_USD":"","BasicUSD":"3.99","StandardUSD":"7.99","PremiumUSD":"9.99","MobileCNY":"21.53","With_Ads_CNY":"","BasicCNY":"28.73","StandardCNY":"57.52","PremiumCNY":"71.92","Code":"SH","Translation":"圣赫勒拿岛"},{"Country":"Sudan","Currency":"USD","Mobile":"","Standard with ads":"","Basic":"3.99","Standard":"7.99","Premium":"9.99","Extra member slots":"","MobileUSD":"","With_Ads_USD":"","BasicUSD":"3.99","StandardUSD":"7.99","PremiumUSD":"9.99","MobileCNY":"","With_Ads_CNY":"","BasicCNY":"28.73","StandardCNY":"57.52","PremiumCNY":"71.92","Code":"SD","Translation":"苏丹"},{"Country":"Tanzania","Currency":"USD","Mobile":"2.99","Standard with ads":"","Basic":"3.99","Standard":"7.99","Premium":"9.99","Extra member slots":"","MobileUSD":"2.99","With_Ads_USD":"","BasicUSD":"3.99","StandardUSD":"7.99","PremiumUSD":"9.99","MobileCNY":"21.53","With_Ads_CNY":"","BasicCNY":"28.73","StandardCNY":"57.52","PremiumCNY":"71.92","Code":"TZ","Translation":"坦桑尼亚"},{"Country":"Timor-Leste","Currency":"USD","Mobile":"2.99","Standard with ads":"","Basic":"3.99","Standard":"7.99","Premium":"9.99","Extra member slots":"","MobileUSD":"2.99","With_Ads_USD":"","BasicUSD":"3.99","StandardUSD":"7.99","PremiumUSD":"9.99","MobileCNY":"21.53","With_Ads_CNY":"","BasicCNY":"28.73","StandardCNY":"57.52","PremiumCNY":"71.92","Code":"TL","Translation":"帝汶读"},{"Country":"Togo","Currency":"USD","Mobile":"2.99","Standard with ads":"","Basic":"3.99","Standard":"7.99","Premium":"9.99","Extra member slots":"","MobileUSD":"2.99","With_Ads_USD":"","BasicUSD":"3.99","StandardUSD":"7.99","PremiumUSD":"9.99","MobileCNY":"21.53","With_Ads_CNY":"","BasicCNY":"28.73","StandardCNY":"57.52","PremiumCNY":"71.92","Code":"TG","Translation":"多哥"},{"Country":"Tonga","Currency":"USD","Mobile":"2.99","Standard with ads":"","Basic":"3.99","Standard":"7.99","Premium":"9.99","Extra member slots":"","MobileUSD":"2.99","With_Ads_USD":"","BasicUSD":"3.99","StandardUSD":"7.99","PremiumUSD":"9.99","MobileCNY":"21.53","With_Ads_CNY":"","BasicCNY":"28.73","StandardCNY":"57.52","PremiumCNY":"71.92","Code":"TO","Translation":"到达的"},{"Country":"Tunisia","Currency":"USD","Mobile":"","Standard with ads":"","Basic":"3.99","Standard":"7.99","Premium":"9.99","Extra member slots":"","MobileUSD":"","With_Ads_USD":"","BasicUSD":"3.99","StandardUSD":"7.99","PremiumUSD":"9.99","MobileCNY":"","With_Ads_CNY":"","BasicCNY":"28.73","StandardCNY":"57.52","PremiumCNY":"71.92","Code":"TN","Translation":"突尼斯"},{"Country":"Tuvalu","Currency":"USD","Mobile":"2.99","Standard with ads":"","Basic":"3.99","Standard":"7.99","Premium":"9.99","Extra member slots":"","MobileUSD":"2.99","With_Ads_USD":"","BasicUSD":"3.99","StandardUSD":"7.99","PremiumUSD":"9.99","MobileCNY":"21.53","With_Ads_CNY":"","BasicCNY":"28.73","StandardCNY":"57.52","PremiumCNY":"71.92","Code":"TV","Translation":"图瓦卢"},{"Country":"Uganda","Currency":"USD","Mobile":"2.99","Standard with ads":"","Basic":"3.99","Standard":"7.99","Premium":"9.99","Extra member slots":"","MobileUSD":"2.99","With_Ads_USD":"","BasicUSD":"3.99","StandardUSD":"7.99","PremiumUSD":"9.99","MobileCNY":"21.53","With_Ads_CNY":"","BasicCNY":"28.73","StandardCNY":"57.52","PremiumCNY":"71.92","Code":"UG","Translation":"乌干达"},{"Country":"Vanuatu","Currency":"USD","Mobile":"2.99","Standard with ads":"","Basic":"3.99","Standard":"7.99","Premium":"9.99","Extra member slots":"","MobileUSD":"2.99","With_Ads_USD":"","BasicUSD":"3.99","StandardUSD":"7.99","PremiumUSD":"9.99","MobileCNY":"21.53","With_Ads_CNY":"","BasicCNY":"28.73","StandardCNY":"57.52","PremiumCNY":"71.92","Code":"VU","Translation":"瓦努阿图"},{"Country":"Wallis & Futuna","Currency":"USD","Mobile":"2.99","Standard with ads":"","Basic":"3.99","Standard":"7.99","Premium":"9.99","Extra member slots":"","MobileUSD":"2.99","With_Ads_USD":"","BasicUSD":"3.99","StandardUSD":"7.99","PremiumUSD":"9.99","MobileCNY":"21.53","With_Ads_CNY":"","BasicCNY":"28.73","StandardCNY":"57.52","PremiumCNY":"71.92","Code":"WF","Translation":"瓦利斯和富图纳群岛"},{"Country":"Yemen","Currency":"USD","Mobile":"","Standard with ads":"","Basic":"3.99","Standard":"7.99","Premium":"9.99","Extra member slots":"","MobileUSD":"","With_Ads_USD":"","BasicUSD":"3.99","StandardUSD":"7.99","PremiumUSD":"9.99","MobileCNY":"","With_Ads_CNY":"","BasicCNY":"28.73","StandardCNY":"57.52","PremiumCNY":"71.92","Code":"YE","Translation":"也门"},{"Country":"Zambia","Currency":"USD","Mobile":"2.99","Standard with ads":"","Basic":"3.99","Standard":"7.99","Premium":"9.99","Extra member slots":"","MobileUSD":"2.99","With_Ads_USD":"","BasicUSD":"3.99","StandardUSD":"7.99","PremiumUSD":"9.99","MobileCNY":"21.53","With_Ads_CNY":"","BasicCNY":"28.73","StandardCNY":"57.52","PremiumCNY":"71.92","Code":"ZM","Translation":"赞比亚"},{"Country":"Zimbabwe","Currency":"USD","Mobile":"2.99","Standard with ads":"","Basic":"3.99","Standard":"7.99","Premium":"9.99","Extra member slots":"","MobileUSD":"2.99","With_Ads_USD":"","BasicUSD":"3.99","StandardUSD":"7.99","PremiumUSD":"9.99","MobileCNY":"21.53","With_Ads_CNY":"","BasicCNY":"28.73","StandardCNY":"57.52","PremiumCNY":"71.92","Code":"ZW","Translation":"津巴布韦"},{"Country":"Iran","Currency":"USD","Mobile":"","Standard with ads":"","Basic":"3.99","Standard":"7.99","Premium":"9.99","Extra member slots":"","MobileUSD":"","With_Ads_USD":"","BasicUSD":"3.99","StandardUSD":"7.99","PremiumUSD":"9.99","MobileCNY":"","With_Ads_CNY":"","BasicCNY":"28.73","StandardCNY":"57.52","PremiumCNY":"71.92","Code":"IR","Translation":"伊朗"},{"Country":"Colombia","Currency":"COP","Mobile":"","Standard with ads":"","Basic":"16900","Standard":"26900","Premium":"38900","Extra member slots":"Standard: 8900 / Premium: 8900","MobileUSD":"","With_Ads_USD":"","BasicUSD":"4.39","StandardUSD":"6.99","PremiumUSD":"10.11","MobileCNY":"","With_Ads_CNY":"","BasicCNY":"31.63","StandardCNY":"50.34","PremiumCNY":"72.80","Code":"CO","Translation":"哥伦比亚"},{"Country":"Vietnam","Currency":"VND","Mobile":"70000","Standard with ads":"","Basic":"108000","Standard":"220000","Premium":"260000","Extra member slots":"","MobileUSD":"2.82","With_Ads_USD":"","BasicUSD":"4.35","StandardUSD":"8.87","PremiumUSD":"10.48","MobileCNY":"20.32","With_Ads_CNY":"","BasicCNY":"31.35","StandardCNY":"63.86","PremiumCNY":"75.48","Code":"VN","Translation":"越南"},{"Country":"South Africa","Currency":"ZAR","Mobile":"49","Standard with ads":"","Basic":"99","Standard":"159","Premium":"199","Extra member slots":"","MobileUSD":"2.62","With_Ads_USD":"","BasicUSD":"5.29","StandardUSD":"8.49","PremiumUSD":"10.63","MobileCNY":"18.56","With_Ads_CNY":"","BasicCNY":"37.49","StandardCNY":"60.21","PremiumCNY":"75.36","Code":"ZA","Translation":"南非"},{"Country":"Albania","Currency":"EUR","Mobile":"","Standard with ads":"","Basic":"4.99","Standard":"7.99","Premium":"9.99","Extra member slots":"","MobileUSD":"","With_Ads_USD":"","BasicUSD":"5.45","StandardUSD":"8.73","PremiumUSD":"10.92","MobileCNY":"","With_Ads_CNY":"","BasicCNY":"38.73","StandardCNY":"62.01","PremiumCNY":"77.53","Code":"AL","Translation":"阿尔巴尼亚"},{"Country":"Bosnia & Herzegovina","Currency":"EUR","Mobile":"","Standard with ads":"","Basic":"4.99","Standard":"7.99","Premium":"9.99","Extra member slots":"","MobileUSD":"","With_Ads_USD":"","BasicUSD":"5.45","StandardUSD":"8.73","PremiumUSD":"10.92","MobileCNY":"","With_Ads_CNY":"","BasicCNY":"38.73","StandardCNY":"62.01","PremiumCNY":"77.53","Code":"BA","Translation":"波斯尼亚和黑塞哥维那"},{"Country":"Bulgaria","Currency":"EUR","Mobile":"","Standard with ads":"","Basic":"4.99","Standard":"7.99","Premium":"9.99","Extra member slots":"","MobileUSD":"","With_Ads_USD":"","BasicUSD":"5.45","StandardUSD":"8.73","PremiumUSD":"10.92","MobileCNY":"","With_Ads_CNY":"","BasicCNY":"38.73","StandardCNY":"62.01","PremiumCNY":"77.53","Code":"BG","Translation":"保加利亚"},{"Country":"Croatia","Currency":"EUR","Mobile":"","Standard with ads":"","Basic":"4.99","Standard":"7.99","Premium":"9.99","Extra member slots":"","MobileUSD":"","With_Ads_USD":"","BasicUSD":"5.45","StandardUSD":"8.73","PremiumUSD":"10.92","MobileCNY":"","With_Ads_CNY":"","BasicCNY":"38.73","StandardCNY":"62.01","PremiumCNY":"77.53","Code":"HR","Translation":"克罗地亚"},{"Country":"Montenegro","Currency":"EUR","Mobile":"","Standard with ads":"","Basic":"4.99","Standard":"7.99","Premium":"9.99","Extra member slots":"","MobileUSD":"","With_Ads_USD":"","BasicUSD":"5.45","StandardUSD":"8.73","PremiumUSD":"10.92","MobileCNY":"","With_Ads_CNY":"","BasicCNY":"38.73","StandardCNY":"62.01","PremiumCNY":"77.53","Code":"ME","Translation":"黑山"},{"Country":"North Macedonia","Currency":"EUR","Mobile":"","Standard with ads":"","Basic":"4.99","Standard":"7.99","Premium":"9.99","Extra member slots":"","MobileUSD":"","With_Ads_USD":"","BasicUSD":"5.45","StandardUSD":"8.73","PremiumUSD":"10.92","MobileCNY":"","With_Ads_CNY":"","BasicCNY":"38.73","StandardCNY":"62.01","PremiumCNY":"77.53","Code":"MK","Translation":"北马其顿"},{"Country":"Serbia","Currency":"EUR","Mobile":"","Standard with ads":"","Basic":"4.99","Standard":"7.99","Premium":"9.99","Extra member slots":"","MobileUSD":"","With_Ads_USD":"","BasicUSD":"5.45","StandardUSD":"8.73","PremiumUSD":"10.92","MobileCNY":"","With_Ads_CNY":"","BasicCNY":"38.73","StandardCNY":"62.01","PremiumCNY":"77.53","Code":"RS","Translation":"塞尔维亚"},{"Country":"Slovenia","Currency":"EUR","Mobile":"","Standard with ads":"","Basic":"4.99","Standard":"7.99","Premium":"9.99","Extra member slots":"","MobileUSD":"","With_Ads_USD":"","BasicUSD":"5.45","StandardUSD":"8.73","PremiumUSD":"10.92","MobileCNY":"","With_Ads_CNY":"","BasicCNY":"38.73","StandardCNY":"62.01","PremiumCNY":"77.53","Code":"SI","Translation":"斯洛文尼亚"},{"Country":"Ukraine","Currency":"EUR","Mobile":"","Standard with ads":"","Basic":"4.99","Standard":"7.49","Premium":"9.99","Extra member slots":"Standard: 2.99 / Premium: 2.99","MobileUSD":"","With_Ads_USD":"","BasicUSD":"5.45","StandardUSD":"8.18","PremiumUSD":"10.92","MobileCNY":"","With_Ads_CNY":"","BasicCNY":"38.73","StandardCNY":"58.13","PremiumCNY":"77.53","Code":"UA","Translation":"乌克兰"},{"Country":"Dominican Republic","Currency":"USD","Mobile":"","Standard with ads":"","Basic":"4.99","Standard":"7.99","Premium":"10.99","Extra member slots":"Standard: 2.99 / Premium: 2.99","MobileUSD":"","With_Ads_USD":"","BasicUSD":"4.99","StandardUSD":"7.99","PremiumUSD":"10.99","MobileCNY":"","With_Ads_CNY":"","BasicCNY":"35.93","StandardCNY":"57.52","PremiumCNY":"79.12","Code":"DO","Translation":"多明尼加共和国"},{"Country":"Ecuador","Currency":"USD","Mobile":"","Standard with ads":"","Basic":"4.99","Standard":"7.99","Premium":"10.99","Extra member slots":"Standard: 2.99 / Premium: 2.99","MobileUSD":"","With_Ads_USD":"","BasicUSD":"4.99","StandardUSD":"7.99","PremiumUSD":"10.99","MobileCNY":"","With_Ads_CNY":"","BasicCNY":"35.93","StandardCNY":"57.52","PremiumCNY":"79.12","Code":"EC","Translation":"厄瓜多尔"},{"Country":"El Salvador","Currency":"USD","Mobile":"","Standard with ads":"","Basic":"4.99","Standard":"7.99","Premium":"10.99","Extra member slots":"Standard: 2.99 / Premium: 2.99","MobileUSD":"","With_Ads_USD":"","BasicUSD":"4.99","StandardUSD":"7.99","PremiumUSD":"10.99","MobileCNY":"","With_Ads_CNY":"","BasicCNY":"35.93","StandardCNY":"57.52","PremiumCNY":"79.12","Code":"SV","Translation":"萨尔瓦多"},{"Country":"Guatemala","Currency":"USD","Mobile":"","Standard with ads":"","Basic":"4.99","Standard":"7.99","Premium":"10.99","Extra member slots":"Standard: 2.99 / Premium: 2.99","MobileUSD":"","With_Ads_USD":"","BasicUSD":"4.99","StandardUSD":"7.99","PremiumUSD":"10.99","MobileCNY":"","With_Ads_CNY":"","BasicCNY":"35.93","StandardCNY":"57.52","PremiumCNY":"79.12","Code":"GT","Translation":"危地马拉"},{"Country":"Honduras","Currency":"USD","Mobile":"","Standard with ads":"","Basic":"4.99","Standard":"7.99","Premium":"10.99","Extra member slots":"Standard: 2.99 / Premium: 2.99","MobileUSD":"","With_Ads_USD":"","BasicUSD":"4.99","StandardUSD":"7.99","PremiumUSD":"10.99","MobileCNY":"","With_Ads_CNY":"","BasicCNY":"35.93","StandardCNY":"57.52","PremiumCNY":"79.12","Code":"HN","Translation":"洪都拉斯"},{"Country":"Brazil","Currency":"BRL","Mobile":"","Standard with ads":"18.90","Basic":"","Standard":"39.90","Premium":"55.90","Extra member slots":"Standard: 12.90 / Premium: 12.90","MobileUSD":"","With_Ads_USD":"3.81","BasicUSD":"","StandardUSD":"8.03","PremiumUSD":"11.25","MobileCNY":"","With_Ads_CNY":"27.40","BasicCNY":"0.00","StandardCNY":"57.84","PremiumCNY":"81.03","Code":"BR","Translation":"巴西"},{"Country":"Thailand","Currency":"THB","Mobile":"99","Standard with ads":"","Basic":"169","Standard":"349","Premium":"419","Extra member slots":"Standard: 99 / Premium: 99","MobileUSD":"2.75","With_Ads_USD":"","BasicUSD":"4.69","StandardUSD":"9.70","PremiumUSD":"11.64","MobileCNY":"19.80","With_Ads_CNY":"","BasicCNY":"33.80","StandardCNY":"69.80","PremiumCNY":"83.80","Code":"TH","Translation":"泰国"},{"Country":"Malaysia","Currency":"MYR","Mobile":"17","Standard with ads":"","Basic":"28","Standard":"45","Premium":"55","Extra member slots":"Standard: 13 / Premium: 13","MobileUSD":"3.61","With_Ads_USD":"","BasicUSD":"5.95","StandardUSD":"9.56","PremiumUSD":"11.68","MobileCNY":"25.59","With_Ads_CNY":"","BasicCNY":"42.14","StandardCNY":"67.73","PremiumCNY":"82.78","Code":"MY","Translation":"马来西亚"},{"Country":"Indonesia","Currency":"IDR","Mobile":"54000","Standard with ads":"","Basic":"65000","Standard":"120000","Premium":"186000","Extra member slots":"","MobileUSD":"3.44","With_Ads_USD":"","BasicUSD":"4.14","StandardUSD":"7.65","PremiumUSD":"11.86","MobileCNY":"24.78","With_Ads_CNY":"","BasicCNY":"29.83","StandardCNY":"55.07","PremiumCNY":"85.36","Code":"ID","Translation":"印度尼西亚"},{"Country":"Hong Kong","Currency":"HKD","Mobile":"","Standard with ads":"","Basic":"63","Standard":"78","Premium":"93","Extra member slots":"Standard: 28 / Premium: 28","MobileUSD":"","With_Ads_USD":"","BasicUSD":"8.06","StandardUSD":"9.97","PremiumUSD":"11.89","MobileCNY":"","With_Ads_CNY":"","BasicCNY":"57.21","StandardCNY":"70.83","PremiumCNY":"84.45","Code":"HK","Translation":"香港"},{"Country":"Macau","Currency":"USD","Mobile":"","Standard with ads":"","Basic":"7.99","Standard":"9.99","Premium":"11.99","Extra member slots":"","MobileUSD":"","With_Ads_USD":"","BasicUSD":"7.99","StandardUSD":"9.99","PremiumUSD":"11.99","MobileCNY":"","With_Ads_CNY":"","BasicCNY":"57.52","StandardCNY":"71.92","PremiumCNY":"86.32","Code":"MO","Translation":"澳门"},{"Country":"Western Sahara","Currency":"USD","Mobile":"","Standard with ads":"","Basic":"7.99","Standard":"9.99","Premium":"11.99","Extra member slots":"","MobileUSD":"","With_Ads_USD":"","BasicUSD":"7.99","StandardUSD":"9.99","PremiumUSD":"11.99","MobileCNY":"","With_Ads_CNY":"","BasicCNY":"57.52","StandardCNY":"71.92","PremiumCNY":"86.32","Code":"EH","Translation":"撒哈拉沙漠西部"},{"Country":"Peru","Currency":"PEN","Mobile":"","Standard with ads":"","Basic":"24.90","Standard":"34.90","Premium":"44.90","Extra member slots":"Standard: 7.90 / Premium: 7.90","MobileUSD":"","With_Ads_USD":"","BasicUSD":"6.79","StandardUSD":"9.51","PremiumUSD":"12.24","MobileCNY":"","With_Ads_CNY":"","BasicCNY":"48.86","StandardCNY":"68.49","PremiumCNY":"88.11","Code":"PE","Translation":"秘鲁"},{"Country":"Chile","Currency":"CLP","Mobile":"","Standard with ads":"","Basic":"6540","Standard":"9190","Premium":"11790","Extra member slots":"Standard: 2620 / Premium: 2620","MobileUSD":"","With_Ads_USD":"","BasicUSD":"6.80","StandardUSD":"9.56","PremiumUSD":"12.26","MobileCNY":"","With_Ads_CNY":"","BasicCNY":"48.97","StandardCNY":"68.81","PremiumCNY":"88.28","Code":"CL","Translation":"智利"},{"Country":"Taiwan","Currency":"TWD","Mobile":"","Standard with ads":"","Basic":"270","Standard":"330","Premium":"390","Extra member slots":"Standard: 100 / Premium: 100","MobileUSD":"","With_Ads_USD":"","BasicUSD":"8.47","StandardUSD":"10.35","PremiumUSD":"12.23","MobileCNY":"","With_Ads_CNY":"","BasicCNY":"60.95","StandardCNY":"74.50","PremiumCNY":"88.04","Code":"TW","Translation":"台湾"},{"Country":"Hungary","Currency":"HUF","Mobile":"","Standard with ads":"","Basic":"2490","Standard":"3490","Premium":"4490","Extra member slots":"Standard: 990 / Premium: 990","MobileUSD":"","With_Ads_USD":"","BasicUSD":"6.91","StandardUSD":"9.68","PremiumUSD":"12.45","MobileCNY":"","With_Ads_CNY":"","BasicCNY":"49.72","StandardCNY":"69.68","PremiumCNY":"89.65","Code":"HU","Translation":"匈牙利"},{"Country":"South Korea","Currency":"KRW","Mobile":"","Standard with ads":"5500","Basic":"","Standard":"13500","Premium":"17000","Extra member slots":"Standard: 5000 / Premium: 5000","MobileUSD":"","With_Ads_USD":"4.15","BasicUSD":"","StandardUSD":"10.18","PremiumUSD":"12.81","MobileCNY":"","With_Ads_CNY":"29.39","BasicCNY":"0.00","StandardCNY":"72.14","PremiumCNY":"90.84","Code":"KR","Translation":"韩国"},{"Country":"Panama","Currency":"USD","Mobile":"","Standard with ads":"","Basic":"4.99","Standard":"8.99","Premium":"12.99","Extra member slots":"Standard: 2.99 / Premium: 2.99","MobileUSD":"","With_Ads_USD":"","BasicUSD":"4.99","StandardUSD":"8.99","PremiumUSD":"12.99","MobileCNY":"","With_Ads_CNY":"","BasicCNY":"35.93","StandardCNY":"64.72","PremiumCNY":"93.52","Code":"PA","Translation":"巴拿马"},{"Country":"Armenia","Currency":"EUR","Mobile":"","Standard with ads":"","Basic":"7.99","Standard":"9.99","Premium":"11.99","Extra member slots":"","MobileUSD":"","With_Ads_USD":"","BasicUSD":"8.73","StandardUSD":"10.92","PremiumUSD":"13.10","MobileCNY":"","With_Ads_CNY":"","BasicCNY":"62.01","StandardCNY":"77.53","PremiumCNY":"93.05","Code":"AM","Translation":"亚美尼亚"},{"Country":"Azerbaijan","Currency":"EUR","Mobile":"","Standard with ads":"","Basic":"7.99","Standard":"9.99","Premium":"11.99","Extra member slots":"","MobileUSD":"","With_Ads_USD":"","BasicUSD":"8.73","StandardUSD":"10.92","PremiumUSD":"13.10","MobileCNY":"","With_Ads_CNY":"","BasicCNY":"62.01","StandardCNY":"77.53","PremiumCNY":"93.05","Code":"AZ","Translation":"阿塞拜疆"},{"Country":"Belarus","Currency":"EUR","Mobile":"","Standard with ads":"","Basic":"7.99","Standard":"9.99","Premium":"11.99","Extra member slots":"","MobileUSD":"","With_Ads_USD":"","BasicUSD":"8.73","StandardUSD":"10.92","PremiumUSD":"13.10","MobileCNY":"","With_Ads_CNY":"","BasicCNY":"62.01","StandardCNY":"77.53","PremiumCNY":"93.05","Code":"BY","Translation":"白俄罗斯"},{"Country":"Estonia","Currency":"EUR","Mobile":"","Standard with ads":"","Basic":"7.99","Standard":"9.99","Premium":"11.99","Extra member slots":"","MobileUSD":"","With_Ads_USD":"","BasicUSD":"8.73","StandardUSD":"10.92","PremiumUSD":"13.10","MobileCNY":"","With_Ads_CNY":"","BasicCNY":"62.01","StandardCNY":"77.53","PremiumCNY":"93.05","Code":"EE","Translation":"爱沙尼亚"},{"Country":"Kazakhstan","Currency":"EUR","Mobile":"","Standard with ads":"","Basic":"7.99","Standard":"9.99","Premium":"11.99","Extra member slots":"","MobileUSD":"","With_Ads_USD":"","BasicUSD":"8.73","StandardUSD":"10.92","PremiumUSD":"13.10","MobileCNY":"","With_Ads_CNY":"","BasicCNY":"62.01","StandardCNY":"77.53","PremiumCNY":"93.05","Code":"KZ","Translation":"哈萨克斯坦"},{"Country":"Kyrgyzstan","Currency":"EUR","Mobile":"","Standard with ads":"","Basic":"7.99","Standard":"9.99","Premium":"11.99","Extra member slots":"","MobileUSD":"","With_Ads_USD":"","BasicUSD":"8.73","StandardUSD":"10.92","PremiumUSD":"13.10","MobileCNY":"","With_Ads_CNY":"","BasicCNY":"62.01","StandardCNY":"77.53","PremiumCNY":"93.05","Code":"KG","Translation":"吉尔吉斯斯坦"},{"Country":"Latvia","Currency":"EUR","Mobile":"","Standard with ads":"","Basic":"7.99","Standard":"9.99","Premium":"11.99","Extra member slots":"","MobileUSD":"","With_Ads_USD":"","BasicUSD":"8.73","StandardUSD":"10.92","PremiumUSD":"13.10","MobileCNY":"","With_Ads_CNY":"","BasicCNY":"62.01","StandardCNY":"77.53","PremiumCNY":"93.05","Code":"LV","Translation":"拉脱维亚"},{"Country":"Lithuania","Currency":"EUR","Mobile":"","Standard with ads":"","Basic":"7.99","Standard":"9.99","Premium":"11.99","Extra member slots":"","MobileUSD":"","With_Ads_USD":"","BasicUSD":"8.73","StandardUSD":"10.92","PremiumUSD":"13.10","MobileCNY":"","With_Ads_CNY":"","BasicCNY":"62.01","StandardCNY":"77.53","PremiumCNY":"93.05","Code":"LT","Translation":"立陶宛"},{"Country":"Moldova","Currency":"EUR","Mobile":"","Standard with ads":"","Basic":"7.99","Standard":"9.99","Premium":"11.99","Extra member slots":"","MobileUSD":"","With_Ads_USD":"","BasicUSD":"8.73","StandardUSD":"10.92","PremiumUSD":"13.10","MobileCNY":"","With_Ads_CNY":"","BasicCNY":"62.01","StandardCNY":"77.53","PremiumCNY":"93.05","Code":"MD","Translation":"摩尔达维亚"},{"Country":"Romania","Currency":"EUR","Mobile":"","Standard with ads":"","Basic":"4.99","Standard":"9.99","Premium":"11.99","Extra member slots":"Standard: 2.99 / Premium: 2.99","MobileUSD":"","With_Ads_USD":"","BasicUSD":"5.45","StandardUSD":"10.92","PremiumUSD":"13.10","MobileCNY":"","With_Ads_CNY":"","BasicCNY":"38.73","StandardCNY":"77.53","PremiumCNY":"93.05","Code":"RO","Translation":"罗马尼亚"},{"Country":"Slovakia","Currency":"EUR","Mobile":"","Standard with ads":"","Basic":"7.99","Standard":"9.99","Premium":"11.99","Extra member slots":"","MobileUSD":"","With_Ads_USD":"","BasicUSD":"8.73","StandardUSD":"10.92","PremiumUSD":"13.10","MobileCNY":"","With_Ads_CNY":"","BasicCNY":"62.01","StandardCNY":"77.53","PremiumCNY":"93.05","Code":"SK","Translation":"斯洛伐克"},{"Country":"Turkmenistan","Currency":"EUR","Mobile":"","Standard with ads":"","Basic":"7.99","Standard":"9.99","Premium":"11.99","Extra member slots":"","MobileUSD":"","With_Ads_USD":"","BasicUSD":"8.73","StandardUSD":"10.92","PremiumUSD":"13.10","MobileCNY":"","With_Ads_CNY":"","BasicCNY":"62.01","StandardCNY":"77.53","PremiumCNY":"93.05","Code":"TM","Translation":"土库曼斯坦"},{"Country":"Uzbekistan","Currency":"EUR","Mobile":"","Standard with ads":"","Basic":"7.99","Standard":"9.99","Premium":"11.99","Extra member slots":"","MobileUSD":"","With_Ads_USD":"","BasicUSD":"8.73","StandardUSD":"10.92","PremiumUSD":"13.10","MobileCNY":"","With_Ads_CNY":"","BasicCNY":"62.01","StandardCNY":"77.53","PremiumCNY":"93.05","Code":"UZ","Translation":"乌兹别克斯坦"},{"Country":"Japan","Currency":"JPY","Mobile":"","Standard with ads":"790","Basic":"","Standard":"1490","Premium":"1980","Extra member slots":"","MobileUSD":"","With_Ads_USD":"5.22","BasicUSD":"","StandardUSD":"9.85","PremiumUSD":"13.09","MobileCNY":"","With_Ads_CNY":"37.60","BasicCNY":"0.00","StandardCNY":"70.92","PremiumCNY":"94.24","Code":"JP","Translation":"日本"},{"Country":"Czechia","Currency":"CZK","Mobile":"","Standard with ads":"","Basic":"199.00","Standard":"259.00","Premium":"319.00","Extra member slots":"Standard: 79 / Premium: 79","MobileUSD":"","With_Ads_USD":"","BasicUSD":"8.62","StandardUSD":"11.22","PremiumUSD":"13.82","MobileCNY":"","With_Ads_CNY":"","BasicCNY":"62.08","StandardCNY":"80.80","PremiumCNY":"99.52","Code":"CZ","Translation":"捷克"},{"Country":"Brunei","Currency":"USD","Mobile":"4.99","Standard with ads":"","Basic":"8.99","Standard":"11.99","Premium":"13.99","Extra member slots":"","MobileUSD":"4.99","With_Ads_USD":"","BasicUSD":"8.99","StandardUSD":"11.99","PremiumUSD":"13.99","MobileCNY":"35.93","With_Ads_CNY":"","BasicCNY":"64.72","StandardCNY":"86.32","PremiumCNY":"100.72","Code":"BN","Translation":"文莱"},{"Country":"French Polynesia","Currency":"USD","Mobile":"4.99","Standard with ads":"","Basic":"8.99","Standard":"11.99","Premium":"13.99","Extra member slots":"","MobileUSD":"4.99","With_Ads_USD":"","BasicUSD":"8.99","StandardUSD":"11.99","PremiumUSD":"13.99","MobileCNY":"35.93","With_Ads_CNY":"","BasicCNY":"64.72","StandardCNY":"86.32","PremiumCNY":"100.72","Code":"PF","Translation":"法属波利尼西亚"},{"Country":"Maldives","Currency":"USD","Mobile":"4.99","Standard with ads":"","Basic":"8.99","Standard":"11.99","Premium":"13.99","Extra member slots":"","MobileUSD":"4.99","With_Ads_USD":"","BasicUSD":"8.99","StandardUSD":"11.99","PremiumUSD":"13.99","MobileCNY":"35.93","With_Ads_CNY":"","BasicCNY":"64.72","StandardCNY":"86.32","PremiumCNY":"100.72","Code":"MV","Translation":"马尔代夫"},{"Country":"Nauru","Currency":"USD","Mobile":"4.99","Standard with ads":"","Basic":"8.99","Standard":"11.99","Premium":"13.99","Extra member slots":"","MobileUSD":"4.99","With_Ads_USD":"","BasicUSD":"8.99","StandardUSD":"11.99","PremiumUSD":"13.99","MobileCNY":"35.93","With_Ads_CNY":"","BasicCNY":"64.72","StandardCNY":"86.32","PremiumCNY":"100.72","Code":"NR","Translation":"瑙鲁"},{"Country":"New Caledonia","Currency":"USD","Mobile":"4.99","Standard with ads":"","Basic":"8.99","Standard":"11.99","Premium":"13.99","Extra member slots":"","MobileUSD":"4.99","With_Ads_USD":"","BasicUSD":"8.99","StandardUSD":"11.99","PremiumUSD":"13.99","MobileCNY":"35.93","With_Ads_CNY":"","BasicCNY":"64.72","StandardCNY":"86.32","PremiumCNY":"100.72","Code":"NC","Translation":"新喀里多尼亚"},{"Country":"Bouvet Island","Currency":"NOK","Mobile":"","Standard with ads":"","Basic":"89","Standard":"109","Premium":"159","Extra member slots":"","MobileUSD":"","With_Ads_USD":"","BasicUSD":"8.44","StandardUSD":"10.34","PremiumUSD":"15.08","MobileCNY":"","With_Ads_CNY":"","BasicCNY":"60.79","StandardCNY":"74.45","PremiumCNY":"108.60","Code":"BV","Translation":"布维岛"},{"Country":"Norway","Currency":"NOK","Mobile":"","Standard with ads":"","Basic":"89","Standard":"109","Premium":"159","Extra member slots":"Standard: 39 / Premium: 39","MobileUSD":"","With_Ads_USD":"","BasicUSD":"8.44","StandardUSD":"10.34","PremiumUSD":"15.08","MobileCNY":"","With_Ads_CNY":"","BasicCNY":"60.79","StandardCNY":"74.45","PremiumCNY":"108.60","Code":"NO","Translation":"挪威"},{"Country":"Svalbard & Jan Mayen","Currency":"NOK","Mobile":"","Standard with ads":"","Basic":"89","Standard":"109","Premium":"159","Extra member slots":"","MobileUSD":"","With_Ads_USD":"","BasicUSD":"8.44","StandardUSD":"10.34","PremiumUSD":"15.08","MobileCNY":"","With_Ads_CNY":"","BasicCNY":"60.79","StandardCNY":"74.45","PremiumCNY":"108.60","Code":"SJ","Translation":"斯瓦尔巴群岛和扬马延岛"},{"Country":"Kuwait","Currency":"USD","Mobile":"","Standard with ads":"","Basic":"7.99","Standard":"9.99","Premium":"14.99","Extra member slots":"","MobileUSD":"","With_Ads_USD":"","BasicUSD":"7.99","StandardUSD":"9.99","PremiumUSD":"14.99","MobileCNY":"","With_Ads_CNY":"","BasicCNY":"57.52","StandardCNY":"71.92","PremiumCNY":"107.92","Code":"KW","Translation":"科威特"},{"Country":"Qatar","Currency":"USD","Mobile":"","Standard with ads":"","Basic":"7.99","Standard":"9.99","Premium":"14.99","Extra member slots":"","MobileUSD":"","With_Ads_USD":"","BasicUSD":"7.99","StandardUSD":"9.99","PremiumUSD":"14.99","MobileCNY":"","With_Ads_CNY":"","BasicCNY":"57.52","StandardCNY":"71.92","PremiumCNY":"107.92","Code":"QA","Translation":"卡塔尔"},{"Country":"Australia","Currency":"AUD","Mobile":"","Standard with ads":"6.99","Basic":"","Standard":"16.99","Premium":"22.99","Extra member slots":"Standard: 7.99 / Premium: 7.99","MobileUSD":"","With_Ads_USD":"4.63","BasicUSD":"","StandardUSD":"11.25","PremiumUSD":"15.22","MobileCNY":"","With_Ads_CNY":"33.32","BasicCNY":"0.00","StandardCNY":"80.98","PremiumCNY":"109.57","Code":"AU","Translation":"澳大利亚"},{"Country":"Cocos (Keeling) Islands","Currency":"AUD","Mobile":"","Standard with ads":"","Basic":"10.99","Standard":"16.99","Premium":"22.99","Extra member slots":"Standard: 7.99 / Premium: 7.99","MobileUSD":"","With_Ads_USD":"","BasicUSD":"7.28","StandardUSD":"11.25","PremiumUSD":"15.22","MobileCNY":"","With_Ads_CNY":"","BasicCNY":"52.38","StandardCNY":"80.98","PremiumCNY":"109.57","Code":"CC","Translation":"科科斯（基林）群岛"},{"Country":"Norfolk Island","Currency":"AUD","Mobile":"","Standard with ads":"","Basic":"10.99","Standard":"16.99","Premium":"22.99","Extra member slots":"Standard: 7.99 / Premium: 7.99","MobileUSD":"","With_Ads_USD":"","BasicUSD":"7.28","StandardUSD":"11.25","PremiumUSD":"15.22","MobileCNY":"","With_Ads_CNY":"","BasicCNY":"52.38","StandardCNY":"80.98","PremiumCNY":"109.57","Code":"NF","Translation":"诺福克岛"},{"Country":"Poland","Currency":"PLN","Mobile":"","Standard with ads":"","Basic":"29","Standard":"43","Premium":"60","Extra member slots":"Standard: 9.99 / Premium: 9.99","MobileUSD":"","With_Ads_USD":"","BasicUSD":"7.35","StandardUSD":"10.90","PremiumUSD":"15.20","MobileCNY":"","With_Ads_CNY":"","BasicCNY":"52.91","StandardCNY":"78.45","PremiumCNY":"109.46","Code":"PL","Translation":"波兰"},{"Country":"Cook Islands","Currency":"NZD","Mobile":"","Standard with ads":"","Basic":"12.99","Standard":"18.49","Premium":"24.99","Extra member slots":"Standard: 7.99 / Premium: 7.99","MobileUSD":"","With_Ads_USD":"","BasicUSD":"7.91","StandardUSD":"11.26","PremiumUSD":"15.22","MobileCNY":"","With_Ads_CNY":"","BasicCNY":"56.97","StandardCNY":"81.09","PremiumCNY":"109.60","Code":"CK","Translation":"库克群岛"},{"Country":"Niue","Currency":"NZD","Mobile":"","Standard with ads":"","Basic":"12.99","Standard":"18.49","Premium":"24.99","Extra member slots":"Standard: 7.99 / Premium: 7.99","MobileUSD":"","With_Ads_USD":"","BasicUSD":"7.91","StandardUSD":"11.26","PremiumUSD":"15.22","MobileCNY":"","With_Ads_CNY":"","BasicCNY":"56.97","StandardCNY":"81.09","PremiumCNY":"109.60","Code":"NU","Translation":"纽埃"},{"Country":"Tokelau","Currency":"NZD","Mobile":"","Standard with ads":"","Basic":"12.99","Standard":"18.49","Premium":"24.99","Extra member slots":"Standard: 7.99 / Premium: 7.99","MobileUSD":"","With_Ads_USD":"","BasicUSD":"7.91","StandardUSD":"11.26","PremiumUSD":"15.22","MobileCNY":"","With_Ads_CNY":"","BasicCNY":"56.97","StandardCNY":"81.09","PremiumCNY":"109.60","Code":"TK","Translation":"托克劳"},{"Country":"Cyprus","Currency":"EUR","Mobile":"","Standard with ads":"","Basic":"7.99","Standard":"10.99","Premium":"13.99","Extra member slots":"","MobileUSD":"","With_Ads_USD":"","BasicUSD":"8.73","StandardUSD":"12.01","PremiumUSD":"15.29","MobileCNY":"","With_Ads_CNY":"","BasicCNY":"62.01","StandardCNY":"85.29","PremiumCNY":"108.57","Code":"CY","Translation":"塞浦路斯"},{"Country":"Georgia","Currency":"EUR","Mobile":"","Standard with ads":"","Basic":"9.39","Standard":"11.79","Premium":"13.99","Extra member slots":"","MobileUSD":"","With_Ads_USD":"","BasicUSD":"10.26","StandardUSD":"12.88","PremiumUSD":"15.29","MobileCNY":"","With_Ads_CNY":"","BasicCNY":"72.87","StandardCNY":"91.50","PremiumCNY":"108.57","Code":"GE","Translation":"乔治亚州"},{"Country":"Greece","Currency":"EUR","Mobile":"","Standard with ads":"","Basic":"7.99","Standard":"10.99","Premium":"13.99","Extra member slots":"","MobileUSD":"","With_Ads_USD":"","BasicUSD":"8.73","StandardUSD":"12.01","PremiumUSD":"15.29","MobileCNY":"","With_Ads_CNY":"","BasicCNY":"62.01","StandardCNY":"85.29","PremiumCNY":"108.57","Code":"GR","Translation":"希腊"},{"Country":"Tajikistan","Currency":"EUR","Mobile":"","Standard with ads":"","Basic":"9.39","Standard":"11.79","Premium":"13.99","Extra member slots":"","MobileUSD":"","With_Ads_USD":"","BasicUSD":"10.26","StandardUSD":"12.88","PremiumUSD":"15.29","MobileCNY":"","With_Ads_CNY":"","BasicCNY":"72.87","StandardCNY":"91.50","PremiumCNY":"108.57","Code":"TJ","Translation":"塔吉克斯坦"},{"Country":"United Arab Emirates","Currency":"AED","Mobile":"","Standard with ads":"","Basic":"29","Standard":"39","Premium":"56","Extra member slots":"","MobileUSD":"","With_Ads_USD":"","BasicUSD":"7.90","StandardUSD":"10.62","PremiumUSD":"15.25","MobileCNY":"","With_Ads_CNY":"","BasicCNY":"56.85","StandardCNY":"76.46","PremiumCNY":"109.78","Code":"AE","Translation":"阿拉伯联合酋长国"},{"Country":"Canada","Currency":"CAD","Mobile":"","Standard with ads":"5.99","Basic":"","Standard":"16.49","Premium":"20.99","Extra member slots":"Standard: 7.99 / Premium: 7.99","MobileUSD":"","With_Ads_USD":"4.45","BasicUSD":"","StandardUSD":"12.24","PremiumUSD":"15.58","MobileCNY":"","With_Ads_CNY":"32.01","BasicCNY":"0.00","StandardCNY":"88.11","PremiumCNY":"112.16","Code":"CA","Translation":"加拿大"},{"Country":"Bahrain","Currency":"USD","Mobile":"","Standard with ads":"","Basic":"7.99","Standard":"10.49","Premium":"15.79","Extra member slots":"","MobileUSD":"","With_Ads_USD":"","BasicUSD":"7.99","StandardUSD":"10.49","PremiumUSD":"15.79","MobileCNY":"","With_Ads_CNY":"","BasicCNY":"57.52","StandardCNY":"75.52","PremiumCNY":"113.68","Code":"BH","Translation":"巴林"},{"Country":"Oman","Currency":"USD","Mobile":"","Standard with ads":"","Basic":"8.39","Standard":"10.49","Premium":"15.79","Extra member slots":"","MobileUSD":"","With_Ads_USD":"","BasicUSD":"8.39","StandardUSD":"10.49","PremiumUSD":"15.79","MobileCNY":"","With_Ads_CNY":"","BasicCNY":"60.40","StandardCNY":"75.52","PremiumCNY":"113.68","Code":"OM","Translation":"我自己的"},{"Country":"Anguilla","Currency":"USD","Mobile":"","Standard with ads":"","Basic":"8.99","Standard":"12.99","Premium":"15.99","Extra member slots":"Standard: 3.99 / Premium: 3.99","MobileUSD":"","With_Ads_USD":"","BasicUSD":"8.99","StandardUSD":"12.99","PremiumUSD":"15.99","MobileCNY":"","With_Ads_CNY":"","BasicCNY":"64.72","StandardCNY":"93.52","PremiumCNY":"115.12","Code":"AI","Translation":"安圭拉"},{"Country":"Antigua & Barbuda","Currency":"USD","Mobile":"","Standard with ads":"","Basic":"8.99","Standard":"12.99","Premium":"15.99","Extra member slots":"Standard: 3.99 / Premium: 3.99","MobileUSD":"","With_Ads_USD":"","BasicUSD":"8.99","StandardUSD":"12.99","PremiumUSD":"15.99","MobileCNY":"","With_Ads_CNY":"","BasicCNY":"64.72","StandardCNY":"93.52","PremiumCNY":"115.12","Code":"AG","Translation":"安提瓜和巴布达"},{"Country":"Aruba","Currency":"USD","Mobile":"","Standard with ads":"","Basic":"8.99","Standard":"12.99","Premium":"15.99","Extra member slots":"Standard: 3.99 / Premium: 3.99","MobileUSD":"","With_Ads_USD":"","BasicUSD":"8.99","StandardUSD":"12.99","PremiumUSD":"15.99","MobileCNY":"","With_Ads_CNY":"","BasicCNY":"64.72","StandardCNY":"93.52","PremiumCNY":"115.12","Code":"AW","Translation":"阿鲁巴岛"},{"Country":"Bahamas","Currency":"USD","Mobile":"","Standard with ads":"","Basic":"8.99","Standard":"12.99","Premium":"15.99","Extra member slots":"Standard: 3.99 / Premium: 3.99","MobileUSD":"","With_Ads_USD":"","BasicUSD":"8.99","StandardUSD":"12.99","PremiumUSD":"15.99","MobileCNY":"","With_Ads_CNY":"","BasicCNY":"64.72","StandardCNY":"93.52","PremiumCNY":"115.12","Code":"BS","Translation":"巴哈马"},{"Country":"Bermuda","Currency":"USD","Mobile":"","Standard with ads":"","Basic":"8.99","Standard":"12.99","Premium":"15.99","Extra member slots":"Standard: 3.99 / Premium: 3.99","MobileUSD":"","With_Ads_USD":"","BasicUSD":"8.99","StandardUSD":"12.99","PremiumUSD":"15.99","MobileCNY":"","With_Ads_CNY":"","BasicCNY":"64.72","StandardCNY":"93.52","PremiumCNY":"115.12","Code":"BM","Translation":"百慕大"},{"Country":"British Virgin Islands","Currency":"USD","Mobile":"","Standard with ads":"","Basic":"8.99","Standard":"12.99","Premium":"15.99","Extra member slots":"Standard: 3.99 / Premium: 3.99","MobileUSD":"","With_Ads_USD":"","BasicUSD":"8.99","StandardUSD":"12.99","PremiumUSD":"15.99","MobileCNY":"","With_Ads_CNY":"","BasicCNY":"64.72","StandardCNY":"93.52","PremiumCNY":"115.12","Code":"VG","Translation":"英属维尔京群岛"},{"Country":"Caribbean Netherlands","Currency":"USD","Mobile":"","Standard with ads":"","Basic":"8.99","Standard":"12.99","Premium":"15.99","Extra member slots":"Standard: 3.99 / Premium: 3.99","MobileUSD":"","With_Ads_USD":"","BasicUSD":"8.99","StandardUSD":"12.99","PremiumUSD":"15.99","MobileCNY":"","With_Ads_CNY":"","BasicCNY":"64.72","StandardCNY":"93.52","PremiumCNY":"115.12","Code":"BQ","Translation":"加勒比荷兰"},{"Country":"Cayman Islands","Currency":"USD","Mobile":"","Standard with ads":"","Basic":"8.99","Standard":"12.99","Premium":"15.99","Extra member slots":"Standard: 3.99 / Premium: 3.99","MobileUSD":"","With_Ads_USD":"","BasicUSD":"8.99","StandardUSD":"12.99","PremiumUSD":"15.99","MobileCNY":"","With_Ads_CNY":"","BasicCNY":"64.72","StandardCNY":"93.52","PremiumCNY":"115.12","Code":"KY","Translation":"开曼群岛"},{"Country":"Costa Rica","Currency":"USD","Mobile":"","Standard with ads":"","Basic":"8.99","Standard":"12.99","Premium":"15.99","Extra member slots":"Standard: 2.99 / Premium: 2.99","MobileUSD":"","With_Ads_USD":"","BasicUSD":"8.99","StandardUSD":"12.99","PremiumUSD":"15.99","MobileCNY":"","With_Ads_CNY":"","BasicCNY":"64.72","StandardCNY":"93.52","PremiumCNY":"115.12","Code":"CR","Translation":"哥斯达黎加"},{"Country":"Curaçao","Currency":"USD","Mobile":"","Standard with ads":"","Basic":"8.99","Standard":"12.99","Premium":"15.99","Extra member slots":"Standard: 3.99 / Premium: 3.99","MobileUSD":"","With_Ads_USD":"","BasicUSD":"8.99","StandardUSD":"12.99","PremiumUSD":"15.99","MobileCNY":"","With_Ads_CNY":"","BasicCNY":"64.72","StandardCNY":"93.52","PremiumCNY":"115.12","Code":"CW","Translation":"库拉索"},{"Country":"Montserrat","Currency":"USD","Mobile":"","Standard with ads":"","Basic":"8.99","Standard":"12.99","Premium":"15.99","Extra member slots":"Standard: 3.99 / Premium: 3.99","MobileUSD":"","With_Ads_USD":"","BasicUSD":"8.99","StandardUSD":"12.99","PremiumUSD":"15.99","MobileCNY":"","With_Ads_CNY":"","BasicCNY":"64.72","StandardCNY":"93.52","PremiumCNY":"115.12","Code":"MS","Translation":"蒙特塞拉特"},{"Country":"Sint Maarten","Currency":"USD","Mobile":"","Standard with ads":"","Basic":"8.99","Standard":"12.99","Premium":"15.99","Extra member slots":"Standard: 3.99 / Premium: 3.99","MobileUSD":"","With_Ads_USD":"","BasicUSD":"8.99","StandardUSD":"12.99","PremiumUSD":"15.99","MobileCNY":"","With_Ads_CNY":"","BasicCNY":"64.72","StandardCNY":"93.52","PremiumCNY":"115.12","Code":"SX","Translation":"圣马丁"},{"Country":"St. Kitts & Nevis","Currency":"USD","Mobile":"","Standard with ads":"","Basic":"8.99","Standard":"12.99","Premium":"15.99","Extra member slots":"Standard: 3.99 / Premium: 3.99","MobileUSD":"","With_Ads_USD":"","BasicUSD":"8.99","StandardUSD":"12.99","PremiumUSD":"15.99","MobileCNY":"","With_Ads_CNY":"","BasicCNY":"64.72","StandardCNY":"93.52","PremiumCNY":"115.12","Code":"KN","Translation":"圣基茨和尼维斯"},{"Country":"Trinidad and Tobago","Currency":"USD","Mobile":"","Standard with ads":"","Basic":"8.99","Standard":"12.99","Premium":"15.99","Extra member slots":"Standard: 3.99 / Premium: 3.99","MobileUSD":"","With_Ads_USD":"","BasicUSD":"8.99","StandardUSD":"12.99","PremiumUSD":"15.99","MobileCNY":"","With_Ads_CNY":"","BasicCNY":"64.72","StandardCNY":"93.52","PremiumCNY":"115.12","Code":"TT","Translation":"特立尼达和多巴哥"},{"Country":"Turks & Caicos Islands","Currency":"USD","Mobile":"","Standard with ads":"","Basic":"8.99","Standard":"12.99","Premium":"15.99","Extra member slots":"Standard: 3.99 / Premium: 3.99","MobileUSD":"","With_Ads_USD":"","BasicUSD":"8.99","StandardUSD":"12.99","PremiumUSD":"15.99","MobileCNY":"","With_Ads_CNY":"","BasicCNY":"64.72","StandardCNY":"93.52","PremiumCNY":"115.12","Code":"TC","Translation":"特克斯和凯科斯群岛"},{"Country":"Saudi Arabia","Currency":"SAR","Mobile":"","Standard with ads":"","Basic":"32","Standard":"43","Premium":"61","Extra member slots":"","MobileUSD":"","With_Ads_USD":"","BasicUSD":"8.53","StandardUSD":"11.47","PremiumUSD":"16.27","MobileCNY":"","With_Ads_CNY":"","BasicCNY":"61.43","StandardCNY":"82.55","PremiumCNY":"117.10","Code":"SA","Translation":"沙特阿拉伯"},{"Country":"New Zealand","Currency":"NZD","Mobile":"","Standard with ads":"","Basic":"14.99","Standard":"20.99","Premium":"27.99","Extra member slots":"Standard: 7.99 / Premium: 7.99","MobileUSD":"","With_Ads_USD":"","BasicUSD":"9.13","StandardUSD":"12.79","PremiumUSD":"17.05","MobileCNY":"","With_Ads_CNY":"","BasicCNY":"65.74","StandardCNY":"92.06","PremiumCNY":"122.76","Code":"NZ","Translation":"新西兰"},{"Country":"Sweden","Currency":"SEK","Mobile":"","Standard with ads":"","Basic":"99","Standard":"129","Premium":"179","Extra member slots":"Standard: 49 / Premium: 49","MobileUSD":"","With_Ads_USD":"","BasicUSD":"9.54","StandardUSD":"12.43","PremiumUSD":"17.25","MobileCNY":"","With_Ads_CNY":"","BasicCNY":"68.69","StandardCNY":"89.50","PremiumCNY":"124.19","Code":"SE","Translation":"瑞典"},{"Country":"Åland Islands","Currency":"EUR","Mobile":"","Standard with ads":"","Basic":"7.99","Standard":"11.99","Premium":"15.99","Extra member slots":"","MobileUSD":"","With_Ads_USD":"","BasicUSD":"8.73","StandardUSD":"13.10","PremiumUSD":"17.47","MobileCNY":"","With_Ads_CNY":"","BasicCNY":"62.01","StandardCNY":"93.05","PremiumCNY":"124.09","Code":"AX","Translation":"奥兰群岛"},{"Country":"Finland","Currency":"EUR","Mobile":"","Standard with ads":"","Basic":"7.99","Standard":"11.99","Premium":"15.99","Extra member slots":"Standard: 3.99 / Premium: 3.99","MobileUSD":"","With_Ads_USD":"","BasicUSD":"8.73","StandardUSD":"13.10","PremiumUSD":"17.47","MobileCNY":"","With_Ads_CNY":"","BasicCNY":"62.01","StandardCNY":"93.05","PremiumCNY":"124.09","Code":"FI","Translation":"芬兰"},{"Country":"Netherlands","Currency":"EUR","Mobile":"","Standard with ads":"","Basic":"7.99","Standard":"11.99","Premium":"15.99","Extra member slots":"Standard: 3.99 / Premium: 3.99","MobileUSD":"","With_Ads_USD":"","BasicUSD":"8.73","StandardUSD":"13.10","PremiumUSD":"17.47","MobileCNY":"","With_Ads_CNY":"","BasicCNY":"62.01","StandardCNY":"93.05","PremiumCNY":"124.09","Code":"NL","Translation":"荷兰"},{"Country":"Portugal","Currency":"EUR","Mobile":"","Standard with ads":"","Basic":"7.99","Standard":"11.99","Premium":"15.99","Extra member slots":"Standard: 3.99 / Premium: 3.99","MobileUSD":"","With_Ads_USD":"","BasicUSD":"8.73","StandardUSD":"13.10","PremiumUSD":"17.47","MobileCNY":"","With_Ads_CNY":"","BasicCNY":"62.01","StandardCNY":"93.05","PremiumCNY":"124.09","Code":"PT","Translation":"葡萄牙"},{"Country":"Réunion","Currency":"EUR","Mobile":"","Standard with ads":"","Basic":"8.99","Standard":"12.49","Premium":"15.99","Extra member slots":"Standard: 5.99 / Premium: 5.99","MobileUSD":"","With_Ads_USD":"","BasicUSD":"9.82","StandardUSD":"13.65","PremiumUSD":"17.47","MobileCNY":"","With_Ads_CNY":"","BasicCNY":"69.77","StandardCNY":"96.93","PremiumCNY":"124.09","Code":"RE","Translation":"会议"},{"Country":"Mexico","Currency":"MXN","Mobile":"","Standard with ads":"99","Basic":"","Standard":"219","Premium":"299","Extra member slots":"Standard: 69 / Premium: 69","MobileUSD":"","With_Ads_USD":"5.93","BasicUSD":"","StandardUSD":"13.11","PremiumUSD":"17.91","MobileCNY":"","With_Ads_CNY":"42.03","BasicCNY":"0.00","StandardCNY":"92.98","PremiumCNY":"126.95","Code":"MX","Translation":"墨西哥"},{"Country":"Uruguay","Currency":"USD","Mobile":"","Standard with ads":"","Basic":"9.99","Standard":"13.99","Premium":"17.99","Extra member slots":"Standard: 3.99 / Premium: 3.99","MobileUSD":"","With_Ads_USD":"","BasicUSD":"9.99","StandardUSD":"13.99","PremiumUSD":"17.99","MobileCNY":"","With_Ads_CNY":"","BasicCNY":"71.92","StandardCNY":"100.72","PremiumCNY":"129.52","Code":"UY","Translation":"乌拉圭"},{"Country":"Barbados","Currency":"USD","Mobile":"","Standard with ads":"","Basic":"10.59","Standard":"15.29","Premium":"18.79","Extra member slots":"Standard: 3.99 / Premium: 3.99","MobileUSD":"","With_Ads_USD":"","BasicUSD":"10.59","StandardUSD":"15.29","PremiumUSD":"18.79","MobileCNY":"","With_Ads_CNY":"","BasicCNY":"76.24","StandardCNY":"110.08","PremiumCNY":"135.28","Code":"BB","Translation":"巴巴多斯"},{"Country":"Israel","Currency":"ILS","Mobile":"","Standard with ads":"","Basic":"32.90","Standard":"54.90","Premium":"69.90","Extra member slots":"Standard: 16.90 / Premium: 16.90","MobileUSD":"","With_Ads_USD":"","BasicUSD":"9.06","StandardUSD":"15.11","PremiumUSD":"19.24","MobileCNY":"","With_Ads_CNY":"","BasicCNY":"65.20","StandardCNY":"108.79","PremiumCNY":"138.52","Code":"IL","Translation":"以色列"},{"Country":"Singapore","Currency":"SGD","Mobile":"","Standard with ads":"","Basic":"13.98","Standard":"19.98","Premium":"25.98","Extra member slots":"Standard: 6.98 / Premium: 6.98","MobileUSD":"","With_Ads_USD":"","BasicUSD":"10.44","StandardUSD":"14.93","PremiumUSD":"19.41","MobileCNY":"","With_Ads_CNY":"","BasicCNY":"75.20","StandardCNY":"107.47","PremiumCNY":"139.74","Code":"SG","Translation":"新加坡"},{"Country":"French Guiana","Currency":"EUR","Mobile":"","Standard with ads":"","Basic":"10.99","Standard":"13.49","Premium":"17.99","Extra member slots":"Standard: 5.99 / Premium: 5.99","MobileUSD":"","With_Ads_USD":"","BasicUSD":"12.01","StandardUSD":"14.74","PremiumUSD":"19.66","MobileCNY":"","With_Ads_CNY":"","BasicCNY":"85.29","StandardCNY":"104.69","PremiumCNY":"139.61","Code":"GF","Translation":"法属圭亚那"},{"Country":"Guadeloupe","Currency":"EUR","Mobile":"","Standard with ads":"","Basic":"10.99","Standard":"13.49","Premium":"17.99","Extra member slots":"Standard: 5.99 / Premium: 5.99","MobileUSD":"","With_Ads_USD":"","BasicUSD":"12.01","StandardUSD":"14.74","PremiumUSD":"19.66","MobileCNY":"","With_Ads_CNY":"","BasicCNY":"85.29","StandardCNY":"104.69","PremiumCNY":"139.61","Code":"GP","Translation":"瓜德罗普岛"},{"Country":"Martinique","Currency":"EUR","Mobile":"","Standard with ads":"","Basic":"10.99","Standard":"13.49","Premium":"17.99","Extra member slots":"Standard: 5.99 / Premium: 5.99","MobileUSD":"","With_Ads_USD":"","BasicUSD":"12.01","StandardUSD":"14.74","PremiumUSD":"19.66","MobileCNY":"","With_Ads_CNY":"","BasicCNY":"85.29","StandardCNY":"104.69","PremiumCNY":"139.61","Code":"MQ","Translation":"马提尼克岛"},{"Country":"Mayotte","Currency":"EUR","Mobile":"","Standard with ads":"","Basic":"10.99","Standard":"13.49","Premium":"17.99","Extra member slots":"Standard: 5.99 / Premium: 5.99","MobileUSD":"","With_Ads_USD":"","BasicUSD":"12.01","StandardUSD":"14.74","PremiumUSD":"19.66","MobileCNY":"","With_Ads_CNY":"","BasicCNY":"85.29","StandardCNY":"104.69","PremiumCNY":"139.61","Code":"YT","Translation":"马约特岛"},{"Country":"Andorra","Currency":"EUR","Mobile":"","Standard with ads":"","Basic":"7.99","Standard":"12.99","Premium":"17.99","Extra member slots":"Standard: 5.99 / Premium: 5.99","MobileUSD":"","With_Ads_USD":"","BasicUSD":"8.73","StandardUSD":"14.19","PremiumUSD":"19.66","MobileCNY":"","With_Ads_CNY":"","BasicCNY":"62.01","StandardCNY":"100.81","PremiumCNY":"139.61","Code":"AD","Translation":"安道尔"},{"Country":"Austria","Currency":"EUR","Mobile":"","Standard with ads":"","Basic":"7.99","Standard":"12.99","Premium":"17.99","Extra member slots":"Standard: 4.99 / Premium: 4.99","MobileUSD":"","With_Ads_USD":"","BasicUSD":"8.73","StandardUSD":"14.19","PremiumUSD":"19.66","MobileCNY":"","With_Ads_CNY":"","BasicCNY":"62.01","StandardCNY":"100.81","PremiumCNY":"139.61","Code":"AT","Translation":"奥地利"},{"Country":"Belgium","Currency":"EUR","Mobile":"","Standard with ads":"","Basic":"8.99","Standard":"13.49","Premium":"17.99","Extra member slots":"Standard: 3.99 / Premium: 3.99","MobileUSD":"","With_Ads_USD":"","BasicUSD":"9.82","StandardUSD":"14.74","PremiumUSD":"19.66","MobileCNY":"","With_Ads_CNY":"","BasicCNY":"69.77","StandardCNY":"104.69","PremiumCNY":"139.61","Code":"BE","Translation":"比利时"},{"Country":"Germany","Currency":"EUR","Mobile":"","Standard with ads":"4.99","Basic":"","Standard":"12.99","Premium":"17.99","Extra member slots":"Standard: 4.99 / Premium: 4.99","MobileUSD":"","With_Ads_USD":"5.45","BasicUSD":"","StandardUSD":"14.19","PremiumUSD":"19.66","MobileCNY":"","With_Ads_CNY":"38.73","BasicCNY":"0.00","StandardCNY":"100.81","PremiumCNY":"139.61","Code":"DE","Translation":"德国"},{"Country":"Gibraltar","Currency":"EUR","Mobile":"","Standard with ads":"","Basic":"7.99","Standard":"12.99","Premium":"17.99","Extra member slots":"Standard: 5.99 / Premium: 5.99","MobileUSD":"","With_Ads_USD":"","BasicUSD":"8.73","StandardUSD":"14.19","PremiumUSD":"19.66","MobileCNY":"","With_Ads_CNY":"","BasicCNY":"62.01","StandardCNY":"100.81","PremiumCNY":"139.61","Code":"GI","Translation":"直布罗陀"},{"Country":"Iceland","Currency":"EUR","Mobile":"","Standard with ads":"","Basic":"7.99","Standard":"12.99","Premium":"17.99","Extra member slots":"Standard: 3.99 / Premium: 3.99","MobileUSD":"","With_Ads_USD":"","BasicUSD":"8.73","StandardUSD":"14.19","PremiumUSD":"19.66","MobileCNY":"","With_Ads_CNY":"","BasicCNY":"62.01","StandardCNY":"100.81","PremiumCNY":"139.61","Code":"IS","Translation":"冰岛"},{"Country":"Italy","Currency":"EUR","Mobile":"","Standard with ads":"5.49","Basic":"","Standard":"12.99","Premium":"17.99","Extra member slots":"Standard: 4.99 / Premium: 4.99","MobileUSD":"","With_Ads_USD":"6.00","BasicUSD":"","StandardUSD":"14.19","PremiumUSD":"19.66","MobileCNY":"","With_Ads_CNY":"42.61","BasicCNY":"0.00","StandardCNY":"100.81","PremiumCNY":"139.61","Code":"IT","Translation":"意大利"},{"Country":"Luxembourg","Currency":"EUR","Mobile":"","Standard with ads":"","Basic":"8.99","Standard":"13.49","Premium":"17.99","Extra member slots":"Standard: 3.99 / Premium: 3.99","MobileUSD":"","With_Ads_USD":"","BasicUSD":"9.82","StandardUSD":"14.74","PremiumUSD":"19.66","MobileCNY":"","With_Ads_CNY":"","BasicCNY":"69.77","StandardCNY":"104.69","PremiumCNY":"139.61","Code":"LU","Translation":"卢森堡"},{"Country":"Malta","Currency":"EUR","Mobile":"","Standard with ads":"","Basic":"7.99","Standard":"12.99","Premium":"17.99","Extra member slots":"Standard: 4.99 / Premium: 4.99","MobileUSD":"","With_Ads_USD":"","BasicUSD":"8.73","StandardUSD":"14.19","PremiumUSD":"19.66","MobileCNY":"","With_Ads_CNY":"","BasicCNY":"62.01","StandardCNY":"100.81","PremiumCNY":"139.61","Code":"MT","Translation":"马耳他"},{"Country":"San Marino","Currency":"EUR","Mobile":"","Standard with ads":"","Basic":"7.99","Standard":"12.99","Premium":"17.99","Extra member slots":"Standard: 4.99 / Premium: 4.99","MobileUSD":"","With_Ads_USD":"","BasicUSD":"8.73","StandardUSD":"14.19","PremiumUSD":"19.66","MobileCNY":"","With_Ads_CNY":"","BasicCNY":"62.01","StandardCNY":"100.81","PremiumCNY":"139.61","Code":"SM","Translation":"圣马力诺"},{"Country":"Spain","Currency":"EUR","Mobile":"","Standard with ads":"5.49","Basic":"","Standard":"12.99","Premium":"17.99","Extra member slots":"Standard: 5.99 / Premium: 5.99","MobileUSD":"","With_Ads_USD":"6.00","BasicUSD":"","StandardUSD":"14.19","PremiumUSD":"19.66","MobileCNY":"","With_Ads_CNY":"42.61","BasicCNY":"0.00","StandardCNY":"100.81","PremiumCNY":"139.61","Code":"ES","Translation":"西班牙"},{"Country":"Vatican City","Currency":"EUR","Mobile":"","Standard with ads":"","Basic":"7.99","Standard":"12.99","Premium":"17.99","Extra member slots":"Standard: 4.99 / Premium: 4.99","MobileUSD":"","With_Ads_USD":"","BasicUSD":"8.73","StandardUSD":"14.19","PremiumUSD":"19.66","MobileCNY":"","With_Ads_CNY":"","BasicCNY":"62.01","StandardCNY":"100.81","PremiumCNY":"139.61","Code":"VA","Translation":"梵蒂冈城"},{"Country":"Falkland Islands","Currency":"USD","Mobile":"","Standard with ads":"","Basic":"9.99","Standard":"15.49","Premium":"19.99","Extra member slots":"Standard: 7.99 / Premium: 7.99","MobileUSD":"","With_Ads_USD":"","BasicUSD":"9.99","StandardUSD":"15.49","PremiumUSD":"19.99","MobileCNY":"","With_Ads_CNY":"","BasicCNY":"71.92","StandardCNY":"111.52","PremiumCNY":"143.92","Code":"FK","Translation":"福克兰群岛"},{"Country":"Denmark","Currency":"DKK","Mobile":"","Standard with ads":"","Basic":"79","Standard":"114","Premium":"149","Extra member slots":"Standard: 39 / Premium: 39","MobileUSD":"","With_Ads_USD":"","BasicUSD":"11.57","StandardUSD":"16.70","PremiumUSD":"21.83","MobileCNY":"","With_Ads_CNY":"","BasicCNY":"83.33","StandardCNY":"120.24","PremiumCNY":"157.16","Code":"DK","Translation":"丹麦"},{"Country":"Faroe Islands","Currency":"DKK","Mobile":"","Standard with ads":"","Basic":"79","Standard":"114","Premium":"149","Extra member slots":"","MobileUSD":"","With_Ads_USD":"","BasicUSD":"11.57","StandardUSD":"16.70","PremiumUSD":"21.83","MobileCNY":"","With_Ads_CNY":"","BasicCNY":"83.33","StandardCNY":"120.24","PremiumCNY":"157.16","Code":"FO","Translation":"法罗群岛"},{"Country":"Greenland","Currency":"DKK","Mobile":"","Standard with ads":"","Basic":"79","Standard":"114","Premium":"149","Extra member slots":"Standard: 39 / Premium: 39","MobileUSD":"","With_Ads_USD":"","BasicUSD":"11.57","StandardUSD":"16.70","PremiumUSD":"21.83","MobileCNY":"","With_Ads_CNY":"","BasicCNY":"83.33","StandardCNY":"120.24","PremiumCNY":"157.16","Code":"GL","Translation":"格陵兰"},{"Country":"French Southern Territories","Currency":"EUR","Mobile":"","Standard with ads":"5.99","Basic":"","Standard":"13.49","Premium":"19.99","Extra member slots":"","MobileUSD":"","With_Ads_USD":"6.54","BasicUSD":"","StandardUSD":"14.74","PremiumUSD":"21.84","MobileCNY":"","With_Ads_CNY":"46.49","BasicCNY":"0.00","StandardCNY":"104.69","PremiumCNY":"155.14","Code":"TF","Translation":"法属南部领土"},{"Country":"France","Currency":"EUR","Mobile":"","Standard with ads":"5.99","Basic":"","Standard":"13.49","Premium":"19.99","Extra member slots":"Standard: 5.99 / Premium: 5.99","MobileUSD":"","With_Ads_USD":"6.54","BasicUSD":"","StandardUSD":"14.74","PremiumUSD":"21.84","MobileCNY":"","With_Ads_CNY":"46.49","BasicCNY":"0.00","StandardCNY":"104.69","PremiumCNY":"155.14","Code":"FR","Translation":"法国"},{"Country":"Monaco","Currency":"EUR","Mobile":"","Standard with ads":"","Basic":"10.99","Standard":"13.49","Premium":"19.99","Extra member slots":"Standard: 5.99 / Premium: 5.99","MobileUSD":"","With_Ads_USD":"","BasicUSD":"12.01","StandardUSD":"14.74","PremiumUSD":"21.84","MobileCNY":"","With_Ads_CNY":"","BasicCNY":"85.29","StandardCNY":"104.69","PremiumCNY":"155.14","Code":"MC","Translation":"摩纳哥"},{"Country":"St. Pierre & Miquelon","Currency":"EUR","Mobile":"","Standard with ads":"","Basic":"10.99","Standard":"13.49","Premium":"19.99","Extra member slots":"Standard: 5.99 / Premium: 5.99","MobileUSD":"","With_Ads_USD":"","BasicUSD":"12.01","StandardUSD":"14.74","PremiumUSD":"21.84","MobileCNY":"","With_Ads_CNY":"","BasicCNY":"85.29","StandardCNY":"104.69","PremiumCNY":"155.14","Code":"PM","Translation":"圣皮埃尔和密克隆群岛"},{"Country":"Ireland","Currency":"EUR","Mobile":"","Standard with ads":"","Basic":"8.99","Standard":"14.99","Premium":"20.99","Extra member slots":"Standard: 4.99 / Premium: 4.99","MobileUSD":"","With_Ads_USD":"","BasicUSD":"9.82","StandardUSD":"16.38","PremiumUSD":"22.93","MobileCNY":"","With_Ads_CNY":"","BasicCNY":"69.77","StandardCNY":"116.33","PremiumCNY":"162.90","Code":"IE","Translation":"爱尔兰"},{"Country":"Guernsey","Currency":"GBP","Mobile":"","Standard with ads":"","Basic":"","Standard":"10.99","Premium":"17.99","Extra member slots":"Standard: 4.99 / Premium: 4.99","MobileUSD":"","With_Ads_USD":"","BasicUSD":"","StandardUSD":"14.05","PremiumUSD":"23.00","MobileCNY":"","With_Ads_CNY":"","BasicCNY":"0.00","StandardCNY":"99.77","PremiumCNY":"163.32","Code":"GG","Translation":"根西岛"},{"Country":"Isle of Man","Currency":"GBP","Mobile":"","Standard with ads":"","Basic":"","Standard":"10.99","Premium":"17.99","Extra member slots":"Standard: 4.99 / Premium: 4.99","MobileUSD":"","With_Ads_USD":"","BasicUSD":"","StandardUSD":"14.05","PremiumUSD":"23.00","MobileCNY":"","With_Ads_CNY":"","BasicCNY":"0.00","StandardCNY":"99.77","PremiumCNY":"163.32","Code":"IM","Translation":"马恩岛"},{"Country":"Jersey","Currency":"GBP","Mobile":"","Standard with ads":"","Basic":"","Standard":"10.99","Premium":"17.99","Extra member slots":"Standard: 4.99 / Premium: 4.99","MobileUSD":"","With_Ads_USD":"","BasicUSD":"","StandardUSD":"14.05","PremiumUSD":"23.00","MobileCNY":"","With_Ads_CNY":"","BasicCNY":"0.00","StandardCNY":"99.77","PremiumCNY":"163.32","Code":"JE","Translation":"球衣"},{"Country":"United Kingdom","Currency":"GBP","Mobile":"","Standard with ads":"","Basic":"","Standard":"10.99","Premium":"17.99","Extra member slots":"Standard: 4.99 / Premium: 4.99","MobileUSD":"","With_Ads_USD":"","BasicUSD":"","StandardUSD":"14.05","PremiumUSD":"23.00","MobileCNY":"","With_Ads_CNY":"","BasicCNY":"0.00","StandardCNY":"99.77","PremiumCNY":"163.32","Code":"GB","Translation":"英国"},{"Country":"Heard & McDonald Islands","Currency":"USD","Mobile":"","Standard with ads":"","Basic":"11.99","Standard":"15.49","Premium":"22.99","Extra member slots":"","MobileUSD":"","With_Ads_USD":"","BasicUSD":"11.99","StandardUSD":"15.49","PremiumUSD":"22.99","MobileCNY":"","With_Ads_CNY":"","BasicCNY":"86.32","StandardCNY":"111.52","PremiumCNY":"165.51","Code":"HM","Translation":"赫德岛和麦克唐纳群岛"},{"Country":"South Georgia & South Sandwich Islands","Currency":"USD","Mobile":"","Standard with ads":"","Basic":"11.99","Standard":"15.49","Premium":"22.99","Extra member slots":"","MobileUSD":"","With_Ads_USD":"","BasicUSD":"11.99","StandardUSD":"15.49","PremiumUSD":"22.99","MobileCNY":"","With_Ads_CNY":"","BasicCNY":"86.32","StandardCNY":"111.52","PremiumCNY":"165.51","Code":"GS","Translation":"南乔治亚岛和南桑威奇群岛"},{"Country":"U.S. Outlying Islands","Currency":"USD","Mobile":"","Standard with ads":"","Basic":"11.99","Standard":"15.49","Premium":"22.99","Extra member slots":"","MobileUSD":"","With_Ads_USD":"","BasicUSD":"11.99","StandardUSD":"15.49","PremiumUSD":"22.99","MobileCNY":"","With_Ads_CNY":"","BasicCNY":"86.32","StandardCNY":"111.52","PremiumCNY":"165.51","Code":"UM","Translation":"美国离岛"},{"Country":"American Samoa","Currency":"USD","Mobile":"","Standard with ads":"6.99","Basic":"","Standard":"15.49","Premium":"22.99","Extra member slots":"Standard: 7.99 / Premium: 7.99","MobileUSD":"","With_Ads_USD":"6.99","BasicUSD":"","StandardUSD":"15.49","PremiumUSD":"22.99","MobileCNY":"","With_Ads_CNY":"50.32","BasicCNY":"0.00","StandardCNY":"111.52","PremiumCNY":"165.51","Code":"AS","Translation":"美属萨摩亚"},{"Country":"Guam","Currency":"USD","Mobile":"","Standard with ads":"6.99","Basic":"","Standard":"15.49","Premium":"22.99","Extra member slots":"Standard: 7.99 / Premium: 7.99","MobileUSD":"","With_Ads_USD":"6.99","BasicUSD":"","StandardUSD":"15.49","PremiumUSD":"22.99","MobileCNY":"","With_Ads_CNY":"50.32","BasicCNY":"0.00","StandardCNY":"111.52","PremiumCNY":"165.51","Code":"GU","Translation":"关岛"},{"Country":"Marshall Islands","Currency":"USD","Mobile":"","Standard with ads":"6.99","Basic":"","Standard":"15.49","Premium":"22.99","Extra member slots":"","MobileUSD":"","With_Ads_USD":"6.99","BasicUSD":"","StandardUSD":"15.49","PremiumUSD":"22.99","MobileCNY":"","With_Ads_CNY":"50.32","BasicCNY":"0.00","StandardCNY":"111.52","PremiumCNY":"165.51","Code":"MH","Translation":"马绍尔群岛"},{"Country":"Micronesia","Currency":"USD","Mobile":"","Standard with ads":"6.99","Basic":"","Standard":"15.49","Premium":"22.99","Extra member slots":"Standard: 7.99 / Premium: 7.99","MobileUSD":"","With_Ads_USD":"6.99","BasicUSD":"","StandardUSD":"15.49","PremiumUSD":"22.99","MobileCNY":"","With_Ads_CNY":"50.32","BasicCNY":"0.00","StandardCNY":"111.52","PremiumCNY":"165.51","Code":"FM","Translation":"密克罗尼西亚"},{"Country":"Northern Mariana Islands","Currency":"USD","Mobile":"","Standard with ads":"6.99","Basic":"","Standard":"15.49","Premium":"22.99","Extra member slots":"Standard: 7.99 / Premium: 7.99","MobileUSD":"","With_Ads_USD":"6.99","BasicUSD":"","StandardUSD":"15.49","PremiumUSD":"22.99","MobileCNY":"","With_Ads_CNY":"50.32","BasicCNY":"0.00","StandardCNY":"111.52","PremiumCNY":"165.51","Code":"MP","Translation":"北马里亚纳群岛"},{"Country":"Palau","Currency":"USD","Mobile":"","Standard with ads":"6.99","Basic":"","Standard":"15.49","Premium":"22.99","Extra member slots":"Standard: 7.99 / Premium: 7.99","MobileUSD":"","With_Ads_USD":"6.99","BasicUSD":"","StandardUSD":"15.49","PremiumUSD":"22.99","MobileCNY":"","With_Ads_CNY":"50.32","BasicCNY":"0.00","StandardCNY":"111.52","PremiumCNY":"165.51","Code":"PW","Translation":"帕劳"},{"Country":"Puerto Rico","Currency":"USD","Mobile":"","Standard with ads":"6.99","Basic":"","Standard":"15.49","Premium":"22.99","Extra member slots":"Standard: 7.99 / Premium: 7.99","MobileUSD":"","With_Ads_USD":"6.99","BasicUSD":"","StandardUSD":"15.49","PremiumUSD":"22.99","MobileCNY":"","With_Ads_CNY":"50.32","BasicCNY":"0.00","StandardCNY":"111.52","PremiumCNY":"165.51","Code":"PR","Translation":"波多黎各"},{"Country":"U.S. Virgin Islands","Currency":"USD","Mobile":"","Standard with ads":"6.99","Basic":"","Standard":"15.49","Premium":"22.99","Extra member slots":"Standard: 7.99 / Premium: 7.99","MobileUSD":"","With_Ads_USD":"6.99","BasicUSD":"","StandardUSD":"15.49","PremiumUSD":"22.99","MobileCNY":"","With_Ads_CNY":"50.32","BasicCNY":"0.00","StandardCNY":"111.52","PremiumCNY":"165.51","Code":"VI","Translation":"美属维尔京群岛"},{"Country":"United States","Currency":"USD","Mobile":"","Standard with ads":"6.99","Basic":"","Standard":"15.49","Premium":"22.99","Extra member slots":"Standard: 7.99 / Premium: 7.99","MobileUSD":"","With_Ads_USD":"6.99","BasicUSD":"","StandardUSD":"15.49","PremiumUSD":"22.99","MobileCNY":"","With_Ads_CNY":"50.32","BasicCNY":"0.00","StandardCNY":"111.52","PremiumCNY":"165.51","Code":"US","Translation":"美国"},{"Country":"Liechtenstein","Currency":"CHF","Mobile":"","Standard with ads":"","Basic":"11.90","Standard":"18.90","Premium":"24.90","Extra member slots":"Standard: 5.90 / Premium: 5.90","MobileUSD":"","With_Ads_USD":"","BasicUSD":"13.43","StandardUSD":"21.34","PremiumUSD":"28.11","MobileCNY":"","With_Ads_CNY":"","BasicCNY":"96.72","StandardCNY":"153.61","PremiumCNY":"202.38","Code":"LI","Translation":"列支敦士登"},{"Country":"Switzerland","Currency":"CHF","Mobile":"","Standard with ads":"","Basic":"11.90","Standard":"18.90","Premium":"24.90","Extra member slots":"Standard: 5.90 / Premium: 5.90","MobileUSD":"","With_Ads_USD":"","BasicUSD":"13.43","StandardUSD":"21.34","PremiumUSD":"28.11","MobileCNY":"","With_Ads_CNY":"","BasicCNY":"96.72","StandardCNY":"153.61","PremiumCNY":"202.38","Code":"CH","Translation":"瑞士"}]